[
  {
    "fw": 5020,
    "mver": "2.2.1",
    "lts": 17,
    "endtime": 1648279353,
    "dst_name": "ul.su",
    "ttr": 163.987511,
    "proto": "TCP",
    "af": 4,
    "size": 0,
    "paris_id": 0,
    "result": [
      {
        "error": "name resolution failed: non-recoverable failure in name resolution"
      }
    ],
    "msm_id": 39735306,
    "prb_id": 1000869,
    "timestamp": 1648279353,
    "msm_name": "Traceroute",
    "from": "185.123.187.2",
    "type": "traceroute",
    "group_id": 39735306,
    "stored_timestamp": 1648279355,
    "probe_data": {
      "address_v4": "185.123.187.2",
      "address_v6": "2a03:9120:0:1:cc75:1bff:fe90:2aa",
      "asn_v4": 43232,
      "asn_v6": 43232,
      "country_code": "BY",
      "description": "Televid",
      "first_connected": 1597407753,
      "geometry": {
        "type": "Point",
        "coordinates": [
          30.3805,
          52.3715
        ]
      },
      "id": 1000869,
      "is_anchor": false,
      "is_public": true,
      "last_connected": 1648301655,
      "prefix_v4": "185.123.184.0/22",
      "prefix_v6": "2a03:9120::/32",
      "status": {
        "id": 1,
        "name": "Connected",
        "since": "2022-03-23T00:27:15Z"
      },
      "status_since": 1647995235,
      "tags": [
        {
          "name": "Cable",
          "slug": "cable"
        },
        {
          "name": "Office",
          "slug": "office"
        },
        {
          "name": "No NAT",
          "slug": "no-nat"
        },
        {
          "name": "Native IPv6",
          "slug": "native-ipv6"
        },
        {
          "name": "dual-stack",
          "slug": "dual-stack"
        },
        {
          "name": "IPv4",
          "slug": "ipv4"
        },
        {
          "name": "IPv6",
          "slug": "ipv6"
        },
        {
          "name": "ISP",
          "slug": "isp"
        },
        {
          "name": "Native IPv4",
          "slug": "native-ipv4"
        },
        {
          "name": "system: IPv4 Stable 90d",
          "slug": "system-ipv4-stable-90d"
        },
        {
          "name": "system: IPv6 Stable 1d",
          "slug": "system-ipv6-stable-1d"
        },
        {
          "name": "system: IPv6 Stable 30d",
          "slug": "system-ipv6-stable-30d"
        },
        {
          "name": "system: Resolves A Correctly",
          "slug": "system-resolves-a-correctly"
        },
        {
          "name": "system: Software",
          "slug": "system-software"
        },
        {
          "name": "system: Resolves AAAA Correctly",
          "slug": "system-resolves-aaaa-correctly"
        },
        {
          "name": "system: IPv4 Capable",
          "slug": "system-ipv4-capable"
        },
        {
          "name": "system: IPv6 Capable",
          "slug": "system-ipv6-capable"
        },
        {
          "name": "system: IPv6 Works",
          "slug": "system-ipv6-works"
        },
        {
          "name": "system: IPv6 Stable 90d",
          "slug": "system-ipv6-stable-90d"
        },
        {
          "name": "system: IPv4 Works",
          "slug": "system-ipv4-works"
        },
        {
          "name": "system: IPv4 Stable 1d",
          "slug": "system-ipv4-stable-1d"
        },
        {
          "name": "system: IPv4 Stable 30d",
          "slug": "system-ipv4-stable-30d"
        }
      ],
      "total_uptime": 50574520,
      "type": "Probe"
    }
  },
  {
    "fw": 5020,
    "mver": "2.2.1",
    "lts": 35,
    "endtime": 1648279354,
    "dst_name": "ul.su",
    "ttr": 604.1526,
    "proto": "TCP",
    "af": 4,
    "size": 0,
    "paris_id": 0,
    "result": [
      {
        "error": "name resolution failed: non-recoverable failure in name resolution"
      }
    ],
    "msm_id": 39735306,
    "prb_id": 1002839,
    "timestamp": 1648279354,
    "msm_name": "Traceroute",
    "from": "82.156.176.91",
    "type": "traceroute",
    "group_id": 39735306,
    "stored_timestamp": 1648279382,
    "probe_data": {
      "address_v4": "82.156.176.91",
      "address_v6": null,
      "asn_v4": 45090,
      "asn_v6": null,
      "country_code": "CN",
      "description": null,
      "first_connected": 1630290677,
      "geometry": {
        "type": "Point",
        "coordinates": [
          113.7185,
          34.7715
        ]
      },
      "id": 1002839,
      "is_anchor": false,
      "is_public": true,
      "last_connected": 1648301712,
      "prefix_v4": "82.156.128.0/18",
      "prefix_v6": null,
      "status": {
        "id": 1,
        "name": "Connected",
        "since": "2022-03-19T03:02:18Z"
      },
      "status_since": 1647658938,
      "tags": [
        {
          "name": "system: Auto GEOIP country",
          "slug": "system-auto-geoip-country"
        },
        {
          "name": "system: IPv4 RFC1918",
          "slug": "system-ipv4-rfc1918"
        },
        {
          "name": "system: Software",
          "slug": "system-software"
        },
        {
          "name": "system: Resolver Mangles Case",
          "slug": "system-resolver-mangles-case"
        },
        {
          "name": "system: IPv4 Capable",
          "slug": "system-ipv4-capable"
        },
        {
          "name": "system: IPv4 Works",
          "slug": "system-ipv4-works"
        }
      ],
      "total_uptime": 17931788,
      "type": "Probe"
    }
  },
  {
    "fw": 5040,
    "mver": "2.4.1",
    "lts": 3,
    "endtime": 1648279351,
    "dst_name": "ul.su",
    "ttr": 257.090602,
    "proto": "TCP",
    "af": 4,
    "size": 0,
    "paris_id": 0,
    "result": [
      {
        "error": "name resolution failed: nodename nor servname provided, or not known"
      }
    ],
    "msm_id": 39735306,
    "prb_id": 12605,
    "timestamp": 1648279351,
    "msm_name": "Traceroute",
    "from": "217.12.205.59",
    "type": "traceroute",
    "group_id": 39735306,
    "stored_timestamp": 1648279354,
    "probe_data": {
      "address_v4": "217.12.205.59",
      "address_v6": null,
      "asn_v4": 15626,
      "asn_v6": null,
      "country_code": "UA",
      "description": "PROBE-KHA",
      "first_connected": 1403695539,
      "geometry": {
        "type": "Point",
        "coordinates": [
          36.2175,
          49.9895
        ]
      },
      "id": 12605,
      "is_anchor": false,
      "is_public": true,
      "last_connected": 1648301949,
      "prefix_v4": "217.12.204.0/23",
      "prefix_v6": null,
      "status": {
        "id": 1,
        "name": "Connected",
        "since": "2022-03-25T22:18:35Z"
      },
      "status_since": 1648246715,
      "tags": [
        {
          "name": "Office",
          "slug": "office"
        },
        {
          "name": "Datacentre",
          "slug": "datacentre"
        },
        {
          "name": "Core",
          "slug": "core"
        },
        {
          "name": "system: IPv4 Stable 90d",
          "slug": "system-ipv4-stable-90d"
        },
        {
          "name": "system: Resolves A Correctly",
          "slug": "system-resolves-a-correctly"
        },
        {
          "name": "system: V3",
          "slug": "system-v3"
        },
        {
          "name": "system: Resolves AAAA Correctly",
          "slug": "system-resolves-aaaa-correctly"
        },
        {
          "name": "system: IPv4 Capable",
          "slug": "system-ipv4-capable"
        },
        {
          "name": "system: IPv4 Works",
          "slug": "system-ipv4-works"
        }
      ],
      "total_uptime": 244419211,
      "type": "Probe"
    }
  },
  {
    "fw": 5040,
    "mver": "2.4.1",
    "lts": 7,
    "endtime": 1648279352,
    "dst_name": "ul.su",
    "ttr": 27.3445,
    "proto": "TCP",
    "af": 4,
    "size": 0,
    "paris_id": 0,
    "result": [
      {
        "error": "name resolution failed: non-recoverable failure in name resolution"
      }
    ],
    "msm_id": 39735306,
    "prb_id": 19166,
    "timestamp": 1648279352,
    "msm_name": "Traceroute",
    "from": "195.211.195.103",
    "type": "traceroute",
    "group_id": 39735306,
    "stored_timestamp": 1648279354,
    "probe_data": {
      "address_v4": "195.211.195.103",
      "address_v6": null,
      "asn_v4": 35640,
      "asn_v6": null,
      "country_code": "RU",
      "description": "my own probe",
      "first_connected": 1428440520,
      "geometry": {
        "type": "Point",
        "coordinates": [
          37.4205,
          55.8805
        ]
      },
      "id": 19166,
      "is_anchor": false,
      "is_public": true,
      "last_connected": 1648301656,
      "prefix_v4": "195.211.195.0/24",
      "prefix_v6": null,
      "status": {
        "id": 1,
        "name": "Connected",
        "since": "2022-03-24T10:20:31Z"
      },
      "status_since": 1648117231,
      "tags": [
        {
          "name": "system: IPv4 Stable 90d",
          "slug": "system-ipv4-stable-90d"
        },
        {
          "name": "system: Resolves A Correctly",
          "slug": "system-resolves-a-correctly"
        },
        {
          "name": "system: IPv4 RFC1918",
          "slug": "system-ipv4-rfc1918"
        },
        {
          "name": "system: V3",
          "slug": "system-v3"
        },
        {
          "name": "system: Resolves AAAA Correctly",
          "slug": "system-resolves-aaaa-correctly"
        },
        {
          "name": "system: IPv4 Capable",
          "slug": "system-ipv4-capable"
        },
        {
          "name": "system: IPv4 Works",
          "slug": "system-ipv4-works"
        },
        {
          "name": "system: IPv4 Stable 30d",
          "slug": "system-ipv4-stable-30d"
        }
      ],
      "total_uptime": 147178080,
      "type": "Probe"
    }
  },
  {
    "fw": 5040,
    "mver": "2.4.1",
    "lts": 76,
    "endtime": 1648279352,
    "dst_name": "ul.su",
    "ttr": 30.642691,
    "proto": "TCP",
    "af": 4,
    "size": 0,
    "paris_id": 0,
    "result": [
      {
        "error": "name resolution failed: non-recoverable failure in name resolution"
      }
    ],
    "msm_id": 39735306,
    "prb_id": 19997,
    "timestamp": 1648279352,
    "msm_name": "Traceroute",
    "from": "92.38.58.196",
    "type": "traceroute",
    "group_id": 39735306,
    "stored_timestamp": 1648279354,
    "probe_data": {
      "address_v4": "92.38.58.196",
      "address_v6": null,
      "asn_v4": 49711,
      "asn_v6": null,
      "country_code": "BY",
      "description": "flynet-home",
      "first_connected": 1417351923,
      "geometry": {
        "type": "Point",
        "coordinates": [
          27.4515,
          53.8505
        ]
      },
      "id": 19997,
      "is_anchor": false,
      "is_public": true,
      "last_connected": 1648301670,
      "prefix_v4": "92.38.56.0/21",
      "prefix_v6": null,
      "status": {
        "id": 1,
        "name": "Connected",
        "since": "2022-03-23T00:35:47Z"
      },
      "status_since": 1647995747,
      "tags": [
        {
          "name": "Home",
          "slug": "home"
        },
        {
          "name": "NAT",
          "slug": "nat"
        },
        {
          "name": "system: IPv4 Stable 90d",
          "slug": "system-ipv4-stable-90d"
        },
        {
          "name": "system: Resolves A Correctly",
          "slug": "system-resolves-a-correctly"
        },
        {
          "name": "system: IPv4 RFC1918",
          "slug": "system-ipv4-rfc1918"
        },
        {
          "name": "system: V3",
          "slug": "system-v3"
        },
        {
          "name": "system: Resolves AAAA Correctly",
          "slug": "system-resolves-aaaa-correctly"
        },
        {
          "name": "system: IPv4 Capable",
          "slug": "system-ipv4-capable"
        },
        {
          "name": "system: IPv4 Works",
          "slug": "system-ipv4-works"
        },
        {
          "name": "system: IPv4 Stable 1d",
          "slug": "system-ipv4-stable-1d"
        },
        {
          "name": "system: IPv4 Stable 30d",
          "slug": "system-ipv4-stable-30d"
        }
      ],
      "total_uptime": 228134280,
      "type": "Probe"
    }
  },
  {
    "fw": 5040,
    "mver": "2.4.1",
    "lts": 33,
    "endtime": 1648279354,
    "dst_name": "ul.su",
    "ttr": 304.487118,
    "proto": "TCP",
    "af": 4,
    "size": 0,
    "paris_id": 0,
    "result": [
      {
        "error": "name resolution failed: nodename nor servname provided, or not known"
      }
    ],
    "msm_id": 39735306,
    "prb_id": 25262,
    "timestamp": 1648279354,
    "msm_name": "Traceroute",
    "from": "46.114.163.3",
    "type": "traceroute",
    "group_id": 39735306,
    "stored_timestamp": 1648279353,
    "probe_data": {
      "address_v4": "46.114.163.3",
      "address_v6": null,
      "asn_v4": 6805,
      "asn_v6": null,
      "country_code": "DE",
      "description": "clutterbox",
      "first_connected": 1447754301,
      "geometry": {
        "type": "Point",
        "coordinates": [
          8.8405,
          51.5685
        ]
      },
      "id": 25262,
      "is_anchor": false,
      "is_public": true,
      "last_connected": 1648301777,
      "prefix_v4": "46.114.0.0/15",
      "prefix_v6": null,
      "status": {
        "id": 1,
        "name": "Connected",
        "since": "2022-03-25T19:05:05Z"
      },
      "status_since": 1648235105,
      "tags": [
        {
          "name": "Mobile",
          "slug": "mobile"
        },
        {
          "name": "Home",
          "slug": "home"
        },
        {
          "name": "NAT",
          "slug": "nat"
        },
        {
          "name": "IPv4",
          "slug": "ipv4"
        },
        {
          "name": "Double-NAT",
          "slug": "double-nat"
        },
        {
          "name": "LTE",
          "slug": "lte"
        },
        {
          "name": "4G",
          "slug": "4g"
        },
        {
          "name": "system: Resolves A Correctly",
          "slug": "system-resolves-a-correctly"
        },
        {
          "name": "system: IPv4 RFC1918",
          "slug": "system-ipv4-rfc1918"
        },
        {
          "name": "system: V3",
          "slug": "system-v3"
        },
        {
          "name": "system: Resolves AAAA Correctly",
          "slug": "system-resolves-aaaa-correctly"
        },
        {
          "name": "system: IPv4 Capable",
          "slug": "system-ipv4-capable"
        },
        {
          "name": "system: IPv4 Works",
          "slug": "system-ipv4-works"
        },
        {
          "name": "system: IPv4 Stable 1d",
          "slug": "system-ipv4-stable-1d"
        },
        {
          "name": "system: IPv4 Stable 30d",
          "slug": "system-ipv4-stable-30d"
        }
      ],
      "total_uptime": 141222123,
      "type": "Probe"
    }
  },
  {
    "fw": 5040,
    "mver": "2.4.1",
    "lts": 4,
    "endtime": 1648279352,
    "dst_name": "ul.su",
    "ttr": 2.76794,
    "proto": "TCP",
    "af": 4,
    "size": 0,
    "paris_id": 0,
    "result": [
      {
        "error": "name resolution failed: non-recoverable failure in name resolution"
      }
    ],
    "msm_id": 39735306,
    "prb_id": 35722,
    "timestamp": 1648279352,
    "msm_name": "Traceroute",
    "from": "195.12.59.245",
    "type": "traceroute",
    "group_id": 39735306,
    "stored_timestamp": 1648279354,
    "probe_data": {
      "address_v4": null,
      "address_v6": null,
      "asn_v4": 48648,
      "asn_v6": null,
      "country_code": "UA",
      "description": "",
      "first_connected": 1532933763,
      "geometry": {
        "type": "Point",
        "coordinates": [
          30.5885,
          50.4585
        ]
      },
      "id": 35722,
      "is_anchor": false,
      "is_public": false,
      "last_connected": 1648301629,
      "prefix_v4": "195.12.56.0/22",
      "prefix_v6": null,
      "status": {
        "id": 1,
        "name": "Connected",
        "since": "2022-03-26T12:30:39Z"
      },
      "status_since": 1648297839,
      "tags": [
        {
          "name": "Cable",
          "slug": "cable"
        },
        {
          "name": "NAT",
          "slug": "nat"
        },
        {
          "name": "system: Resolves A Correctly",
          "slug": "system-resolves-a-correctly"
        },
        {
          "name": "system: IPv4 RFC1918",
          "slug": "system-ipv4-rfc1918"
        },
        {
          "name": "system: V3",
          "slug": "system-v3"
        },
        {
          "name": "system: Resolves AAAA Correctly",
          "slug": "system-resolves-aaaa-correctly"
        },
        {
          "name": "system: IPv4 Capable",
          "slug": "system-ipv4-capable"
        },
        {
          "name": "system: IPv4 Works",
          "slug": "system-ipv4-works"
        }
      ],
      "total_uptime": 28857449,
      "type": "Probe"
    }
  },
  {
    "fw": 5040,
    "mver": "2.4.1",
    "lts": 43,
    "endtime": 1648279352,
    "dst_name": "ul.su",
    "ttr": 530.377417,
    "proto": "TCP",
    "af": 4,
    "size": 0,
    "paris_id": 0,
    "result": [
      {
        "error": "name resolution failed: non-recoverable failure in name resolution"
      }
    ],
    "msm_id": 39735306,
    "prb_id": 52159,
    "timestamp": 1648279352,
    "msm_name": "Traceroute",
    "from": "112.196.163.119",
    "type": "traceroute",
    "group_id": 39735306,
    "stored_timestamp": 1648279355,
    "probe_data": {
      "address_v4": "103.61.113.23",
      "address_v6": null,
      "asn_v4": 45184,
      "asn_v6": null,
      "country_code": "IN",
      "description": "",
      "first_connected": 1608022019,
      "geometry": {
        "type": "Point",
        "coordinates": [
          86.1795,
          23.6815
        ]
      },
      "id": 52159,
      "is_anchor": false,
      "is_public": true,
      "last_connected": 1648296983,
      "prefix_v4": "103.61.113.0/24",
      "prefix_v6": null,
      "status": {
        "id": 2,
        "name": "Disconnected",
        "since": "2022-03-26T12:16:23Z"
      },
      "status_since": 1648296983,
      "tags": [
        {
          "name": "system: Resolves A Correctly",
          "slug": "system-resolves-a-correctly"
        },
        {
          "name": "system: IPv4 RFC1918",
          "slug": "system-ipv4-rfc1918"
        },
        {
          "name": "system: V4",
          "slug": "system-v4"
        },
        {
          "name": "system: Resolves AAAA Correctly",
          "slug": "system-resolves-aaaa-correctly"
        },
        {
          "name": "system: IPv4 Capable",
          "slug": "system-ipv4-capable"
        },
        {
          "name": "system: IPv4 Works",
          "slug": "system-ipv4-works"
        }
      ],
      "total_uptime": 32676997,
      "type": "Probe"
    }
  },
  {
    "fw": 5040,
    "mver": "2.4.1",
    "lts": 13,
    "endtime": 1648279353,
    "dst_name": "ul.su",
    "ttr": 63.969376,
    "proto": "TCP",
    "af": 4,
    "size": 0,
    "paris_id": 0,
    "result": [
      {
        "error": "name resolution failed: non-recoverable failure in name resolution"
      }
    ],
    "msm_id": 39735306,
    "prb_id": 52284,
    "timestamp": 1648279353,
    "msm_name": "Traceroute",
    "from": "37.214.78.133",
    "type": "traceroute",
    "group_id": 39735306,
    "stored_timestamp": 1648279356,
    "probe_data": {
      "address_v4": "37.214.78.133",
      "address_v6": "2a02:220f:2000:af00:1:a1ff:fec7:38cb",
      "asn_v4": 6697,
      "asn_v6": 6697,
      "country_code": "BY",
      "description": "wolfmeister.dev",
      "first_connected": 1610115323,
      "geometry": {
        "type": "Point",
        "coordinates": [
          27.6315,
          53.9095
        ]
      },
      "id": 52284,
      "is_anchor": false,
      "is_public": true,
      "last_connected": 1648301648,
      "prefix_v4": "37.214.78.0/23",
      "prefix_v6": "2a02:2208::/29",
      "status": {
        "id": 1,
        "name": "Connected",
        "since": "2022-03-18T01:07:34Z"
      },
      "status_since": 1647565654,
      "tags": [
        {
          "name": "Fibre",
          "slug": "fibre"
        },
        {
          "name": "Home",
          "slug": "home"
        },
        {
          "name": "IPv4",
          "slug": "ipv4"
        },
        {
          "name": "IPv6",
          "slug": "ipv6"
        },
        {
          "name": "system: IPv6 Stable 1d",
          "slug": "system-ipv6-stable-1d"
        },
        {
          "name": "system: IPv6 Stable 30d",
          "slug": "system-ipv6-stable-30d"
        },
        {
          "name": "system: Resolves A Correctly",
          "slug": "system-resolves-a-correctly"
        },
        {
          "name": "system: IPv4 RFC1918",
          "slug": "system-ipv4-rfc1918"
        },
        {
          "name": "system: V4",
          "slug": "system-v4"
        },
        {
          "name": "system: Resolves AAAA Correctly",
          "slug": "system-resolves-aaaa-correctly"
        },
        {
          "name": "system: IPv4 Capable",
          "slug": "system-ipv4-capable"
        },
        {
          "name": "system: IPv6 Capable",
          "slug": "system-ipv6-capable"
        },
        {
          "name": "system: IPv6 Works",
          "slug": "system-ipv6-works"
        },
        {
          "name": "system: IPv4 Works",
          "slug": "system-ipv4-works"
        },
        {
          "name": "system: IPv4 Stable 1d",
          "slug": "system-ipv4-stable-1d"
        }
      ],
      "total_uptime": 38037632,
      "type": "Probe"
    }
  },
  {
    "fw": 5040,
    "mver": "2.4.1",
    "lts": 55,
    "endtime": 1648279352,
    "dst_name": "ul.su",
    "ttr": 185.336709,
    "proto": "TCP",
    "af": 4,
    "size": 0,
    "paris_id": 0,
    "result": [
      {
        "error": "name resolution failed: non-recoverable failure in name resolution"
      }
    ],
    "msm_id": 39735306,
    "prb_id": 53857,
    "timestamp": 1648279352,
    "msm_name": "Traceroute",
    "from": "185.179.215.11",
    "type": "traceroute",
    "group_id": 39735306,
    "stored_timestamp": 1648279355,
    "probe_data": {
      "address_v4": "185.179.215.11",
      "address_v6": null,
      "asn_v4": 213024,
      "asn_v6": null,
      "country_code": "UA",
      "description": "StarTelecom ISP, Mukachevo",
      "first_connected": 1590954338,
      "geometry": {
        "type": "Point",
        "coordinates": [
          22.7295,
          48.4405
        ]
      },
      "id": 53857,
      "is_anchor": false,
      "is_public": true,
      "last_connected": 1648301870,
      "prefix_v4": "185.179.215.0/24",
      "prefix_v6": null,
      "status": {
        "id": 1,
        "name": "Connected",
        "since": "2022-03-26T11:14:58Z"
      },
      "status_since": 1648293298,
      "tags": [
        {
          "name": "Fibre",
          "slug": "fibre"
        },
        {
          "name": "Datacentre",
          "slug": "datacentre"
        },
        {
          "name": "NAT",
          "slug": "nat"
        },
        {
          "name": "IPv4",
          "slug": "ipv4"
        },
        {
          "name": "ISP",
          "slug": "isp"
        },
        {
          "name": "system: Resolves A Correctly",
          "slug": "system-resolves-a-correctly"
        },
        {
          "name": "system: IPv4 RFC1918",
          "slug": "system-ipv4-rfc1918"
        },
        {
          "name": "system: V4",
          "slug": "system-v4"
        },
        {
          "name": "system: Resolves AAAA Correctly",
          "slug": "system-resolves-aaaa-correctly"
        },
        {
          "name": "system: IPv4 Capable",
          "slug": "system-ipv4-capable"
        },
        {
          "name": "system: IPv4 Works",
          "slug": "system-ipv4-works"
        }
      ],
      "total_uptime": 57305808,
      "type": "Probe"
    }
  },
  {
    "fw": 5040,
    "mver": "2.4.1",
    "lts": 9,
    "endtime": 1648279352,
    "dst_name": "ul.su",
    "ttr": 23.006125,
    "proto": "TCP",
    "af": 4,
    "size": 0,
    "paris_id": 0,
    "result": [
      {
        "error": "name resolution failed: non-recoverable failure in name resolution"
      }
    ],
    "msm_id": 39735306,
    "prb_id": 54451,
    "timestamp": 1648279352,
    "msm_name": "Traceroute",
    "from": "178.69.214.238",
    "type": "traceroute",
    "group_id": 39735306,
    "stored_timestamp": 1648279353,
    "probe_data": {
      "address_v4": "178.69.214.238",
      "address_v6": null,
      "asn_v4": 12389,
      "asn_v6": null,
      "country_code": "RU",
      "description": "",
      "first_connected": 1580837539,
      "geometry": {
        "type": "Point",
        "coordinates": [
          37.9095,
          59.1275
        ]
      },
      "id": 54451,
      "is_anchor": false,
      "is_public": true,
      "last_connected": 1648302007,
      "prefix_v4": "178.69.128.0/17",
      "prefix_v6": null,
      "status": {
        "id": 1,
        "name": "Connected",
        "since": "2022-02-10T01:14:53Z"
      },
      "status_since": 1644455693,
      "tags": [
        {
          "name": "system: IPv4 Stable 90d",
          "slug": "system-ipv4-stable-90d"
        },
        {
          "name": "system: Resolves A Correctly",
          "slug": "system-resolves-a-correctly"
        },
        {
          "name": "system: IPv4 RFC1918",
          "slug": "system-ipv4-rfc1918"
        },
        {
          "name": "system: V4",
          "slug": "system-v4"
        },
        {
          "name": "system: Resolves AAAA Correctly",
          "slug": "system-resolves-aaaa-correctly"
        },
        {
          "name": "system: IPv4 Capable",
          "slug": "system-ipv4-capable"
        },
        {
          "name": "system: IPv4 Works",
          "slug": "system-ipv4-works"
        },
        {
          "name": "system: IPv4 Stable 1d",
          "slug": "system-ipv4-stable-1d"
        },
        {
          "name": "system: IPv4 Stable 30d",
          "slug": "system-ipv4-stable-30d"
        }
      ],
      "total_uptime": 22948852,
      "type": "Probe"
    }
  },
  {
    "fw": 5040,
    "mver": "2.4.1",
    "lts": 65,
    "endtime": 1648279354,
    "dst_name": "ul.su",
    "ttr": 11.944458,
    "proto": "TCP",
    "af": 4,
    "size": 0,
    "paris_id": 0,
    "result": [
      {
        "error": "name resolution failed: non-recoverable failure in name resolution"
      }
    ],
    "msm_id": 39735306,
    "prb_id": 55193,
    "timestamp": 1648279354,
    "msm_name": "Traceroute",
    "from": "46.20.76.1",
    "type": "traceroute",
    "group_id": 39735306,
    "stored_timestamp": 1648279382,
    "probe_data": {
      "address_v4": "46.20.76.1",
      "address_v6": null,
      "asn_v4": 51813,
      "asn_v6": null,
      "country_code": "RU",
      "description": "AlterCPA Office, Saransk, Mordovia, Russia",
      "first_connected": 1585325650,
      "geometry": {
        "type": "Point",
        "coordinates": [
          45.2615,
          54.1885
        ]
      },
      "id": 55193,
      "is_anchor": false,
      "is_public": true,
      "last_connected": 1648301634,
      "prefix_v4": "46.20.76.0/22",
      "prefix_v6": null,
      "status": {
        "id": 1,
        "name": "Connected",
        "since": "2022-03-08T10:58:29Z"
      },
      "status_since": 1646737109,
      "tags": [
        {
          "name": "Cable",
          "slug": "cable"
        },
        {
          "name": "Office",
          "slug": "office"
        },
        {
          "name": "NAT",
          "slug": "nat"
        },
        {
          "name": "IPv4",
          "slug": "ipv4"
        },
        {
          "name": "FTTH",
          "slug": "ftth"
        },
        {
          "name": "system: Resolves A Correctly",
          "slug": "system-resolves-a-correctly"
        },
        {
          "name": "system: IPv4 RFC1918",
          "slug": "system-ipv4-rfc1918"
        },
        {
          "name": "system: V4",
          "slug": "system-v4"
        },
        {
          "name": "system: Resolves AAAA Correctly",
          "slug": "system-resolves-aaaa-correctly"
        },
        {
          "name": "system: IPv4 Capable",
          "slug": "system-ipv4-capable"
        },
        {
          "name": "system: IPv4 Works",
          "slug": "system-ipv4-works"
        },
        {
          "name": "system: IPv4 Stable 1d",
          "slug": "system-ipv4-stable-1d"
        }
      ],
      "total_uptime": 49128670,
      "type": "Probe"
    }
  },
  {
    "fw": 5040,
    "mver": "2.4.1",
    "lts": 679,
    "endtime": 1648279358,
    "dst_name": "ul.su",
    "ttr": 2181.067001,
    "proto": "TCP",
    "af": 4,
    "size": 0,
    "paris_id": 0,
    "result": [
      {
        "error": "name resolution failed: nodename nor servname provided, or not known"
      }
    ],
    "msm_id": 39735306,
    "prb_id": 55798,
    "timestamp": 1648279358,
    "msm_name": "Traceroute",
    "from": "63.152.93.55",
    "type": "traceroute",
    "group_id": 39735306,
    "stored_timestamp": 1648279365,
    "probe_data": {
      "address_v4": null,
      "address_v6": null,
      "asn_v4": 209,
      "asn_v6": null,
      "country_code": "US",
      "description": "",
      "first_connected": 1575691284,
      "geometry": {
        "type": "Point",
        "coordinates": [
          -91.6685,
          41.9815
        ]
      },
      "id": 55798,
      "is_anchor": false,
      "is_public": false,
      "last_connected": 1648301943,
      "prefix_v4": "63.152.0.0/16",
      "prefix_v6": null,
      "status": {
        "id": 1,
        "name": "Connected",
        "since": "2022-03-18T05:35:23Z"
      },
      "status_since": 1647581723,
      "tags": [
        {
          "name": "DSL",
          "slug": "dsl"
        },
        {
          "name": "Home",
          "slug": "home"
        },
        {
          "name": "system: Resolves A Correctly",
          "slug": "system-resolves-a-correctly"
        },
        {
          "name": "system: IPv4 RFC1918",
          "slug": "system-ipv4-rfc1918"
        },
        {
          "name": "system: V4",
          "slug": "system-v4"
        },
        {
          "name": "system: Resolves AAAA Correctly",
          "slug": "system-resolves-aaaa-correctly"
        },
        {
          "name": "system: IPv4 Capable",
          "slug": "system-ipv4-capable"
        },
        {
          "name": "system: IPv4 Works",
          "slug": "system-ipv4-works"
        }
      ],
      "total_uptime": 54742795,
      "type": "Probe"
    }
  }
]