[
  {
    "fw": 5040,
    "mver": "2.4.1",
    "lts": 34,
    "endtime": 1650702059,
    "dst_name": "imctax.parus-s.ru",
    "ttr": 89.40102,
    "proto": "TCP",
    "af": 4,
    "size": 0,
    "paris_id": 0,
    "result": [
      {
        "error": "name resolution failed: nodename nor servname provided, or not known"
      }
    ],
    "msm_id": 40383701,
    "prb_id": 1000876,
    "timestamp": 1650702059,
    "msm_name": "Traceroute",
    "from": "86.57.234.135",
    "type": "traceroute",
    "group_id": 40383701,
    "stored_timestamp": 1650702062,
    "probe_data": {
      "address_v4": "86.57.234.135",
      "address_v6": null,
      "asn_v4": 6697,
      "asn_v6": null,
      "country_code": "BY",
      "description": null,
      "first_connected": 1597417738,
      "geometry": {
        "type": "Point",
        "coordinates": [
          27.4605,
          53.9405
        ]
      },
      "id": 1000876,
      "is_anchor": false,
      "is_public": true,
      "last_connected": 1650720852,
      "prefix_v4": "86.57.234.0/23",
      "prefix_v6": null,
      "status": {
        "id": 1,
        "name": "Connected",
        "since": "2022-03-31T11:05:00Z"
      },
      "status_since": 1648724700,
      "tags": [
        {
          "name": "system: Resolves A Correctly",
          "slug": "system-resolves-a-correctly"
        },
        {
          "name": "system: Resolves AAAA Correctly",
          "slug": "system-resolves-aaaa-correctly"
        },
        {
          "name": "system: IPv4 Capable",
          "slug": "system-ipv4-capable"
        },
        {
          "name": "system: IPv4 RFC1918",
          "slug": "system-ipv4-rfc1918"
        },
        {
          "name": "system: Software",
          "slug": "system-software"
        },
        {
          "name": "system: IPv4 Works",
          "slug": "system-ipv4-works"
        },
        {
          "name": "system: IPv4 Stable 1d",
          "slug": "system-ipv4-stable-1d"
        },
        {
          "name": "system: IPv4 Stable 30d",
          "slug": "system-ipv4-stable-30d"
        }
      ],
      "total_uptime": 40894216,
      "type": "Probe"
    }
  },
  {
    "fw": 5060,
    "mver": "2.5.1",
    "lts": 0,
    "endtime": 1650702059,
    "dst_name": "imctax.parus-s.ru",
    "ttr": 152.84809,
    "proto": "TCP",
    "af": 4,
    "size": 0,
    "paris_id": 0,
    "result": [
      {
        "error": "name resolution failed: nodename nor servname provided, or not known"
      }
    ],
    "msm_id": 40383701,
    "prb_id": 12779,
    "timestamp": 1650702059,
    "msm_name": "Traceroute",
    "from": "91.244.79.232",
    "type": "traceroute",
    "group_id": 40383701,
    "stored_timestamp": 1650702061,
    "probe_data": {
      "address_v4": "91.244.79.232",
      "address_v6": null,
      "asn_v4": 49749,
      "asn_v6": null,
      "country_code": "RU",
      "description": "architecturno",
      "first_connected": 1380733781,
      "geometry": {
        "type": "Point",
        "coordinates": [
          55.1205,
          51.7915
        ]
      },
      "id": 12779,
      "is_anchor": false,
      "is_public": true,
      "last_connected": 1650721046,
      "prefix_v4": "91.244.72.0/21",
      "prefix_v6": null,
      "status": {
        "id": 1,
        "name": "Connected",
        "since": "2022-04-21T20:17:48Z"
      },
      "status_since": 1650572268,
      "tags": [
        {
          "name": "NAT",
          "slug": "nat"
        },
        {
          "name": "system: Resolves A Correctly",
          "slug": "system-resolves-a-correctly"
        },
        {
          "name": "system: Resolves AAAA Correctly",
          "slug": "system-resolves-aaaa-correctly"
        },
        {
          "name": "system: IPv4 Capable",
          "slug": "system-ipv4-capable"
        },
        {
          "name": "system: IPv4 RFC1918",
          "slug": "system-ipv4-rfc1918"
        },
        {
          "name": "system: V3",
          "slug": "system-v3"
        },
        {
          "name": "system: IPv4 Works",
          "slug": "system-ipv4-works"
        }
      ],
      "total_uptime": 123886723,
      "type": "Probe"
    }
  },
  {
    "fw": 5020,
    "mver": "2.2.1",
    "lts": 6,
    "endtime": 1650702058,
    "dst_name": "imctax.parus-s.ru",
    "ttr": 162.22253,
    "proto": "TCP",
    "af": 4,
    "size": 0,
    "paris_id": 0,
    "result": [
      {
        "error": "name resolution failed: nodename nor servname provided, or not known"
      }
    ],
    "msm_id": 40383701,
    "prb_id": 19969,
    "timestamp": 1650702058,
    "msm_name": "Traceroute",
    "from": "185.171.100.29",
    "type": "traceroute",
    "group_id": 40383701,
    "stored_timestamp": 1650702060,
    "probe_data": {
      "address_v4": null,
      "address_v6": null,
      "asn_v4": 61111,
      "asn_v6": null,
      "country_code": "RU",
      "description": "Moscow",
      "first_connected": 1424835348,
      "geometry": {
        "type": "Point",
        "coordinates": [
          37.6105,
          55.8215
        ]
      },
      "id": 19969,
      "is_anchor": false,
      "is_public": false,
      "last_connected": 1650720885,
      "prefix_v4": "185.171.100.0/23",
      "prefix_v6": null,
      "status": {
        "id": 1,
        "name": "Connected",
        "since": "2021-09-30T20:16:41Z"
      },
      "status_since": 1633033001,
      "tags": [
        {
          "name": "Fibre",
          "slug": "fibre"
        },
        {
          "name": "Datacentre",
          "slug": "datacentre"
        },
        {
          "name": "Multihomed",
          "slug": "multihomed"
        },
        {
          "name": "system: IPv4 Stable 90d",
          "slug": "system-ipv4-stable-90d"
        },
        {
          "name": "system: Resolves A Correctly",
          "slug": "system-resolves-a-correctly"
        },
        {
          "name": "system: Resolves AAAA Correctly",
          "slug": "system-resolves-aaaa-correctly"
        },
        {
          "name": "system: IPv4 Capable",
          "slug": "system-ipv4-capable"
        },
        {
          "name": "system: V3",
          "slug": "system-v3"
        },
        {
          "name": "system: IPv4 Works",
          "slug": "system-ipv4-works"
        },
        {
          "name": "system: IPv4 Stable 1d",
          "slug": "system-ipv4-stable-1d"
        },
        {
          "name": "system: IPv4 Stable 30d",
          "slug": "system-ipv4-stable-30d"
        }
      ],
      "total_uptime": 191584252,
      "type": "Probe"
    }
  },
  {
    "fw": 5060,
    "mver": "2.5.1",
    "lts": 5,
    "endtime": 1650702059,
    "dst_name": "imctax.parus-s.ru",
    "ttr": 4.400079,
    "proto": "TCP",
    "af": 4,
    "size": 0,
    "paris_id": 0,
    "result": [
      {
        "error": "name resolution failed: nodename nor servname provided, or not known"
      }
    ],
    "msm_id": 40383701,
    "prb_id": 19977,
    "timestamp": 1650702059,
    "msm_name": "Traceroute",
    "from": "93.84.57.89",
    "type": "traceroute",
    "group_id": 40383701,
    "stored_timestamp": 1650702062,
    "probe_data": {
      "address_v4": "93.84.57.89",
      "address_v6": null,
      "asn_v4": 6697,
      "asn_v6": null,
      "country_code": "BY",
      "description": "Chupaka's Probe",
      "first_connected": 1417180314,
      "geometry": {
        "type": "Point",
        "coordinates": [
          27.6605,
          53.8705
        ]
      },
      "id": 19977,
      "is_anchor": false,
      "is_public": true,
      "last_connected": 1650720901,
      "prefix_v4": "93.84.0.0/18",
      "prefix_v6": null,
      "status": {
        "id": 1,
        "name": "Connected",
        "since": "2022-04-20T02:13:59Z"
      },
      "status_since": 1650420839,
      "tags": [
        {
          "name": "Fibre",
          "slug": "fibre"
        },
        {
          "name": "Home",
          "slug": "home"
        },
        {
          "name": "No NAT",
          "slug": "no-nat"
        },
        {
          "name": "IPv6 Tunnel",
          "slug": "ipv6-tunnel"
        },
        {
          "name": "IPv4",
          "slug": "ipv4"
        },
        {
          "name": "6to4",
          "slug": "6to4"
        },
        {
          "name": "Native IPv4",
          "slug": "native-ipv4"
        },
        {
          "name": "iwantbcp38compliancetesting",
          "slug": "iwantbcp38compliancetesting"
        },
        {
          "name": "system: Resolver Mangles Case",
          "slug": "system-resolver-mangles-case"
        },
        {
          "name": "system: IPv4 Capable",
          "slug": "system-ipv4-capable"
        },
        {
          "name": "system: V3",
          "slug": "system-v3"
        },
        {
          "name": "system: IPv4 Works",
          "slug": "system-ipv4-works"
        },
        {
          "name": "system: IPv4 Stable 1d",
          "slug": "system-ipv4-stable-1d"
        },
        {
          "name": "system: IPv4 Stable 30d",
          "slug": "system-ipv4-stable-30d"
        }
      ],
      "total_uptime": 203894564,
      "type": "Probe"
    }
  },
  {
    "fw": 5060,
    "mver": "2.5.1",
    "lts": 5,
    "endtime": 1650702059,
    "dst_name": "imctax.parus-s.ru",
    "ttr": 113.821575,
    "proto": "TCP",
    "af": 4,
    "size": 0,
    "paris_id": 0,
    "result": [
      {
        "error": "name resolution failed: nodename nor servname provided, or not known"
      }
    ],
    "msm_id": 40383701,
    "prb_id": 29596,
    "timestamp": 1650702059,
    "msm_name": "Traceroute",
    "from": "62.149.31.157",
    "type": "traceroute",
    "group_id": 40383701,
    "stored_timestamp": 1650702062,
    "probe_data": {
      "address_v4": null,
      "address_v6": null,
      "asn_v4": 15497,
      "asn_v6": null,
      "country_code": "UA",
      "description": null,
      "first_connected": 1479294300,
      "geometry": {
        "type": "Point",
        "coordinates": [
          30.5715,
          50.4005
        ]
      },
      "id": 29596,
      "is_anchor": false,
      "is_public": false,
      "last_connected": 1650720916,
      "prefix_v4": "62.149.31.0/24",
      "prefix_v6": null,
      "status": {
        "id": 1,
        "name": "Connected",
        "since": "2022-04-11T10:46:58Z"
      },
      "status_since": 1649674018,
      "tags": [
        {
          "name": "system: Resolves A Correctly",
          "slug": "system-resolves-a-correctly"
        },
        {
          "name": "system: Resolves AAAA Correctly",
          "slug": "system-resolves-aaaa-correctly"
        },
        {
          "name": "system: IPv4 Capable",
          "slug": "system-ipv4-capable"
        },
        {
          "name": "system: V3",
          "slug": "system-v3"
        },
        {
          "name": "system: IPv4 Works",
          "slug": "system-ipv4-works"
        },
        {
          "name": "system: IPv4 Stable 1d",
          "slug": "system-ipv4-stable-1d"
        }
      ],
      "total_uptime": 167990930,
      "type": "Probe"
    }
  },
  {
    "fw": 5060,
    "mver": "2.5.1",
    "lts": 1,
    "endtime": 1650702058,
    "dst_name": "imctax.parus-s.ru",
    "ttr": 23.619237,
    "proto": "TCP",
    "af": 4,
    "size": 0,
    "paris_id": 0,
    "result": [
      {
        "error": "name resolution failed: nodename nor servname provided, or not known"
      }
    ],
    "msm_id": 40383701,
    "prb_id": 29698,
    "timestamp": 1650702058,
    "msm_name": "Traceroute",
    "from": "178.201.110.40",
    "type": "traceroute",
    "group_id": 40383701,
    "stored_timestamp": 1650702061,
    "probe_data": {
      "address_v4": "178.201.110.40",
      "address_v6": null,
      "asn_v4": 3209,
      "asn_v6": null,
      "country_code": "DE",
      "description": "Home",
      "first_connected": 1474729665,
      "geometry": {
        "type": "Point",
        "coordinates": [
          8.9215,
          50.1715
        ]
      },
      "id": 29698,
      "is_anchor": false,
      "is_public": true,
      "last_connected": 1650721102,
      "prefix_v4": "178.200.0.0/15",
      "prefix_v6": null,
      "status": {
        "id": 1,
        "name": "Connected",
        "since": "2022-04-06T08:50:56Z"
      },
      "status_since": 1649235056,
      "tags": [
        {
          "name": "Cable",
          "slug": "cable"
        },
        {
          "name": "Home",
          "slug": "home"
        },
        {
          "name": "NAT",
          "slug": "nat"
        },
        {
          "name": "IPv4",
          "slug": "ipv4"
        },
        {
          "name": "system: IPv4 Stable 90d",
          "slug": "system-ipv4-stable-90d"
        },
        {
          "name": "system: Resolves A Correctly",
          "slug": "system-resolves-a-correctly"
        },
        {
          "name": "system: Resolves AAAA Correctly",
          "slug": "system-resolves-aaaa-correctly"
        },
        {
          "name": "system: IPv4 Capable",
          "slug": "system-ipv4-capable"
        },
        {
          "name": "system: IPv4 RFC1918",
          "slug": "system-ipv4-rfc1918"
        },
        {
          "name": "system: V3",
          "slug": "system-v3"
        },
        {
          "name": "system: IPv4 Works",
          "slug": "system-ipv4-works"
        },
        {
          "name": "system: IPv4 Stable 1d",
          "slug": "system-ipv4-stable-1d"
        },
        {
          "name": "system: IPv4 Stable 30d",
          "slug": "system-ipv4-stable-30d"
        }
      ],
      "total_uptime": 171552439,
      "type": "Probe"
    }
  },
  {
    "fw": 5060,
    "mver": "2.5.1",
    "lts": 29,
    "endtime": 1650702058,
    "dst_name": "imctax.parus-s.ru",
    "ttr": 16.032465,
    "proto": "TCP",
    "af": 4,
    "size": 0,
    "paris_id": 0,
    "result": [
      {
        "error": "name resolution failed: nodename nor servname provided, or not known"
      }
    ],
    "msm_id": 40383701,
    "prb_id": 34854,
    "timestamp": 1650702058,
    "msm_name": "Traceroute",
    "from": "45.152.122.93",
    "type": "traceroute",
    "group_id": 40383701,
    "stored_timestamp": 1650702064,
    "probe_data": {
      "address_v4": "45.152.122.93",
      "address_v6": null,
      "asn_v4": 57456,
      "asn_v6": null,
      "country_code": "RU",
      "description": "",
      "first_connected": 1529344149,
      "geometry": {
        "type": "Point",
        "coordinates": [
          37.7295,
          55.9595
        ]
      },
      "id": 34854,
      "is_anchor": false,
      "is_public": true,
      "last_connected": 1650721029,
      "prefix_v4": "45.152.122.0/24",
      "prefix_v6": null,
      "status": {
        "id": 1,
        "name": "Connected",
        "since": "2022-04-20T19:10:58Z"
      },
      "status_since": 1650481858,
      "tags": [
        {
          "name": "system: IPv4 Stable 90d",
          "slug": "system-ipv4-stable-90d"
        },
        {
          "name": "system: Resolves A Correctly",
          "slug": "system-resolves-a-correctly"
        },
        {
          "name": "system: Resolves AAAA Correctly",
          "slug": "system-resolves-aaaa-correctly"
        },
        {
          "name": "system: IPv4 Capable",
          "slug": "system-ipv4-capable"
        },
        {
          "name": "system: IPv4 RFC1918",
          "slug": "system-ipv4-rfc1918"
        },
        {
          "name": "system: V3",
          "slug": "system-v3"
        },
        {
          "name": "system: IPv4 Works",
          "slug": "system-ipv4-works"
        },
        {
          "name": "system: IPv4 Stable 1d",
          "slug": "system-ipv4-stable-1d"
        },
        {
          "name": "system: IPv4 Stable 30d",
          "slug": "system-ipv4-stable-30d"
        }
      ],
      "total_uptime": 87623579,
      "type": "Probe"
    }
  },
  {
    "fw": 5060,
    "mver": "2.5.1",
    "lts": 53,
    "endtime": 1650702059,
    "dst_name": "imctax.parus-s.ru",
    "ttr": 114.417708,
    "proto": "TCP",
    "af": 4,
    "size": 0,
    "paris_id": 0,
    "result": [
      {
        "error": "name resolution failed: non-recoverable failure in name resolution"
      }
    ],
    "msm_id": 40383701,
    "prb_id": 54359,
    "timestamp": 1650702059,
    "msm_name": "Traceroute",
    "from": "109.108.71.127",
    "type": "traceroute",
    "group_id": 40383701,
    "stored_timestamp": 1650702062,
    "probe_data": {
      "address_v4": "109.108.71.127",
      "address_v6": null,
      "asn_v4": 34056,
      "asn_v6": null,
      "country_code": "UA",
      "description": "",
      "first_connected": 1578337860,
      "geometry": {
        "type": "Point",
        "coordinates": [
          30.5195,
          50.4515
        ]
      },
      "id": 54359,
      "is_anchor": false,
      "is_public": true,
      "last_connected": 1650721050,
      "prefix_v4": "109.108.64.0/19",
      "prefix_v6": null,
      "status": {
        "id": 1,
        "name": "Connected",
        "since": "2022-04-23T04:41:39Z"
      },
      "status_since": 1650688899,
      "tags": [
        {
          "name": "system: Resolves A Correctly",
          "slug": "system-resolves-a-correctly"
        },
        {
          "name": "system: Resolves AAAA Correctly",
          "slug": "system-resolves-aaaa-correctly"
        },
        {
          "name": "system: IPv4 Capable",
          "slug": "system-ipv4-capable"
        },
        {
          "name": "system: IPv4 RFC1918",
          "slug": "system-ipv4-rfc1918"
        },
        {
          "name": "system: V4",
          "slug": "system-v4"
        },
        {
          "name": "system: IPv4 Works",
          "slug": "system-ipv4-works"
        }
      ],
      "total_uptime": 71597739,
      "type": "Probe"
    }
  },
  {
    "fw": 5020,
    "mver": "2.2.1",
    "lts": 5,
    "endtime": 1650702060,
    "dst_name": "imctax.parus-s.ru",
    "ttr": 588.06913,
    "proto": "TCP",
    "af": 4,
    "size": 0,
    "paris_id": 0,
    "result": [
      {
        "error": "name resolution failed: nodename nor servname provided, or not known"
      }
    ],
    "msm_id": 40383701,
    "prb_id": 1002839,
    "timestamp": 1650702060,
    "msm_name": "Traceroute",
    "from": "82.156.176.91",
    "type": "traceroute",
    "group_id": 40383701,
    "stored_timestamp": 1650702061,
    "probe_data": {
      "address_v4": "82.156.176.91",
      "address_v6": null,
      "asn_v4": 45090,
      "asn_v6": null,
      "country_code": "CN",
      "description": null,
      "first_connected": 1630290677,
      "geometry": {
        "type": "Point",
        "coordinates": [
          113.7185,
          34.7715
        ]
      },
      "id": 1002839,
      "is_anchor": false,
      "is_public": true,
      "last_connected": 1650720911,
      "prefix_v4": "82.156.128.0/18",
      "prefix_v6": null,
      "status": {
        "id": 1,
        "name": "Connected",
        "since": "2022-04-04T06:22:21Z"
      },
      "status_since": 1649053341,
      "tags": [
        {
          "name": "system: Auto GEOIP country",
          "slug": "system-auto-geoip-country"
        },
        {
          "name": "system: Resolver Mangles Case",
          "slug": "system-resolver-mangles-case"
        },
        {
          "name": "system: IPv4 Capable",
          "slug": "system-ipv4-capable"
        },
        {
          "name": "system: IPv4 RFC1918",
          "slug": "system-ipv4-rfc1918"
        },
        {
          "name": "system: Software",
          "slug": "system-software"
        },
        {
          "name": "system: IPv4 Works",
          "slug": "system-ipv4-works"
        }
      ],
      "total_uptime": 20350641,
      "type": "Probe"
    }
  },
  {
    "fw": 5060,
    "mver": "2.5.1",
    "lts": 21,
    "endtime": 1650702068,
    "dst_name": "imctax.parus-s.ru",
    "ttr": 10203.23124,
    "proto": "TCP",
    "af": 4,
    "size": 0,
    "paris_id": 0,
    "result": [
      {
        "error": "name resolution failed: nodename nor servname provided, or not known"
      }
    ],
    "msm_id": 40383701,
    "prb_id": 25461,
    "timestamp": 1650702068,
    "msm_name": "Traceroute",
    "from": "212.199.144.158",
    "type": "traceroute",
    "group_id": 40383701,
    "stored_timestamp": 1650702072,
    "probe_data": {
      "address_v4": "212.199.144.158",
      "address_v6": null,
      "asn_v4": 12400,
      "asn_v6": null,
      "country_code": "UA",
      "description": "",
      "first_connected": 1473839725,
      "geometry": {
        "type": "Point",
        "coordinates": [
          36.2105,
          49.9775
        ]
      },
      "id": 25461,
      "is_anchor": false,
      "is_public": true,
      "last_connected": 1650720927,
      "prefix_v4": "212.199.144.0/21",
      "prefix_v6": null,
      "status": {
        "id": 1,
        "name": "Connected",
        "since": "2022-04-17T14:23:28Z"
      },
      "status_since": 1650205408,
      "tags": [
        {
          "name": "system: Resolves A Correctly",
          "slug": "system-resolves-a-correctly"
        },
        {
          "name": "system: Resolves AAAA Correctly",
          "slug": "system-resolves-aaaa-correctly"
        },
        {
          "name": "system: IPv4 Capable",
          "slug": "system-ipv4-capable"
        },
        {
          "name": "system: IPv4 RFC1918",
          "slug": "system-ipv4-rfc1918"
        },
        {
          "name": "system: V3",
          "slug": "system-v3"
        },
        {
          "name": "system: IPv4 Works",
          "slug": "system-ipv4-works"
        }
      ],
      "total_uptime": 144065152,
      "type": "Probe"
    }
  },
  {
    "fw": 5060,
    "mver": "2.5.1",
    "lts": 51,
    "endtime": 1650702061,
    "dst_name": "imctax.parus-s.ru",
    "ttr": 377.134708,
    "proto": "TCP",
    "af": 4,
    "size": 0,
    "paris_id": 0,
    "result": [
      {
        "error": "name resolution failed: non-recoverable failure in name resolution"
      }
    ],
    "msm_id": 40383701,
    "prb_id": 52424,
    "timestamp": 1650702061,
    "msm_name": "Traceroute",
    "from": "142.254.99.126",
    "type": "traceroute",
    "group_id": 40383701,
    "stored_timestamp": 1650702062,
    "probe_data": {
      "address_v4": "142.254.99.126",
      "address_v6": null,
      "asn_v4": 46375,
      "asn_v6": null,
      "country_code": "US",
      "description": "Diana Winn",
      "first_connected": 1646164253,
      "geometry": {
        "type": "Point",
        "coordinates": [
          -122.4215,
          37.7695
        ]
      },
      "id": 52424,
      "is_anchor": false,
      "is_public": true,
      "last_connected": 1650720946,
      "prefix_v4": "142.254.0.0/17",
      "prefix_v6": null,
      "status": {
        "id": 1,
        "name": "Connected",
        "since": "2022-04-16T15:11:58Z"
      },
      "status_since": 1650121918,
      "tags": [
        {
          "name": "system: Resolves A Correctly",
          "slug": "system-resolves-a-correctly"
        },
        {
          "name": "system: Resolves AAAA Correctly",
          "slug": "system-resolves-aaaa-correctly"
        },
        {
          "name": "system: IPv4 Capable",
          "slug": "system-ipv4-capable"
        },
        {
          "name": "system: IPv4 RFC1918",
          "slug": "system-ipv4-rfc1918"
        },
        {
          "name": "system: V4",
          "slug": "system-v4"
        },
        {
          "name": "system: IPv4 Works",
          "slug": "system-ipv4-works"
        },
        {
          "name": "system: IPv4 Stable 30d",
          "slug": "system-ipv4-stable-30d"
        }
      ],
      "total_uptime": 4555743,
      "type": "Probe"
    }
  },
  {
    "fw": 5060,
    "mver": "2.5.1",
    "lts": 50,
    "endtime": 1650702062,
    "dst_name": "imctax.parus-s.ru",
    "ttr": 777.069125,
    "proto": "TCP",
    "af": 4,
    "size": 0,
    "paris_id": 0,
    "result": [
      {
        "error": "name resolution failed: nodename nor servname provided, or not known"
      }
    ],
    "msm_id": 40383701,
    "prb_id": 54484,
    "timestamp": 1650702062,
    "msm_name": "Traceroute",
    "from": "202.153.221.95",
    "type": "traceroute",
    "group_id": 40383701,
    "stored_timestamp": 1650702064,
    "probe_data": {
      "address_v4": "202.153.221.95",
      "address_v6": null,
      "asn_v4": 4764,
      "asn_v6": null,
      "country_code": "AU",
      "description": "Yarraville",
      "first_connected": 1579812020,
      "geometry": {
        "type": "Point",
        "coordinates": [
          144.9715,
          -37.7805
        ]
      },
      "id": 54484,
      "is_anchor": false,
      "is_public": true,
      "last_connected": 1650721172,
      "prefix_v4": "202.153.220.0/23",
      "prefix_v6": null,
      "status": {
        "id": 1,
        "name": "Connected",
        "since": "2022-04-22T14:36:25Z"
      },
      "status_since": 1650638185,
      "tags": [
        {
          "name": "Fibre",
          "slug": "fibre"
        },
        {
          "name": "Home",
          "slug": "home"
        },
        {
          "name": "system: IPv4 Stable 90d",
          "slug": "system-ipv4-stable-90d"
        },
        {
          "name": "system: Resolves A Correctly",
          "slug": "system-resolves-a-correctly"
        },
        {
          "name": "system: Resolves AAAA Correctly",
          "slug": "system-resolves-aaaa-correctly"
        },
        {
          "name": "system: IPv4 Capable",
          "slug": "system-ipv4-capable"
        },
        {
          "name": "system: IPv4 RFC1918",
          "slug": "system-ipv4-rfc1918"
        },
        {
          "name": "system: V4",
          "slug": "system-v4"
        },
        {
          "name": "system: IPv4 Works",
          "slug": "system-ipv4-works"
        },
        {
          "name": "system: IPv4 Stable 1d",
          "slug": "system-ipv4-stable-1d"
        },
        {
          "name": "system: IPv4 Stable 30d",
          "slug": "system-ipv4-stable-30d"
        }
      ],
      "total_uptime": 54320162,
      "type": "Probe"
    }
  },
  {
    "fw": 5060,
    "mver": "2.5.1",
    "lts": 65,
    "endtime": 1650702062,
    "dst_name": "imctax.parus-s.ru",
    "ttr": 31.2285,
    "proto": "TCP",
    "af": 4,
    "size": 0,
    "paris_id": 0,
    "result": [
      {
        "error": "name resolution failed: nodename nor servname provided, or not known"
      }
    ],
    "msm_id": 40383701,
    "prb_id": 55193,
    "timestamp": 1650702062,
    "msm_name": "Traceroute",
    "from": "46.20.76.53",
    "type": "traceroute",
    "group_id": 40383701,
    "stored_timestamp": 1650702075,
    "probe_data": {
      "address_v4": "46.20.76.53",
      "address_v6": null,
      "asn_v4": 51813,
      "asn_v6": null,
      "country_code": "RU",
      "description": "AlterCPA Office, Saransk, Mordovia, Russia",
      "first_connected": 1585325650,
      "geometry": {
        "type": "Point",
        "coordinates": [
          45.2615,
          54.1885
        ]
      },
      "id": 55193,
      "is_anchor": false,
      "is_public": true,
      "last_connected": 1650720891,
      "prefix_v4": "46.20.76.0/22",
      "prefix_v6": null,
      "status": {
        "id": 1,
        "name": "Connected",
        "since": "2022-04-12T06:48:44Z"
      },
      "status_since": 1649746124,
      "tags": [
        {
          "name": "Cable",
          "slug": "cable"
        },
        {
          "name": "Office",
          "slug": "office"
        },
        {
          "name": "NAT",
          "slug": "nat"
        },
        {
          "name": "IPv4",
          "slug": "ipv4"
        },
        {
          "name": "FTTH",
          "slug": "ftth"
        },
        {
          "name": "system: Resolves A Correctly",
          "slug": "system-resolves-a-correctly"
        },
        {
          "name": "system: Resolves AAAA Correctly",
          "slug": "system-resolves-aaaa-correctly"
        },
        {
          "name": "system: IPv4 Capable",
          "slug": "system-ipv4-capable"
        },
        {
          "name": "system: IPv4 RFC1918",
          "slug": "system-ipv4-rfc1918"
        },
        {
          "name": "system: V4",
          "slug": "system-v4"
        },
        {
          "name": "system: IPv4 Works",
          "slug": "system-ipv4-works"
        },
        {
          "name": "system: IPv4 Stable 1d",
          "slug": "system-ipv4-stable-1d"
        },
        {
          "name": "system: IPv4 Stable 30d",
          "slug": "system-ipv4-stable-30d"
        }
      ],
      "total_uptime": 51546473,
      "type": "Probe"
    }
  },
  {
    "fw": 5060,
    "mver": "2.5.1",
    "lts": 26,
    "endtime": 1650702156,
    "dst_name": "imctax.parus-s.ru",
    "ttr": 834.348083,
    "dst_addr": "68.183.247.163",
    "src_addr": "10.40.40.162",
    "proto": "TCP",
    "af": 4,
    "size": 0,
    "paris_id": 1,
    "result": [
      {
        "hop": 1,
        "result": [
          {
            "from": "117.247.236.129",
            "ttl": 254,
            "size": 40,
            "rtt": 2.163,
            "ittl": 0
          },
          {
            "from": "117.247.236.129",
            "ttl": 254,
            "size": 40,
            "rtt": 1.953,
            "ittl": 0
          },
          {
            "from": "117.247.236.129",
            "ttl": 254,
            "size": 40,
            "rtt": 2.127,
            "ittl": 0
          }
        ]
      },
      {
        "hop": 2,
        "result": [
          {
            "x": "*"
          },
          {
            "x": "*"
          },
          {
            "x": "*"
          }
        ]
      },
      {
        "hop": 3,
        "result": [
          {
            "x": "*"
          },
          {
            "x": "*"
          },
          {
            "x": "*"
          }
        ]
      },
      {
        "hop": 4,
        "result": [
          {
            "x": "*"
          },
          {
            "x": "*"
          },
          {
            "x": "*"
          }
        ]
      },
      {
        "hop": 5,
        "result": [
          {
            "x": "*"
          },
          {
            "from": "218.248.62.114",
            "ttl": 59,
            "size": 40,
            "rtt": 25.953
          },
          {
            "from": "218.248.62.114",
            "ttl": 59,
            "size": 40,
            "rtt": 25.44
          }
        ]
      },
      {
        "hop": 6,
        "result": [
          {
            "x": "*"
          },
          {
            "from": "117.247.236.129",
            "ttl": 254,
            "size": 52,
            "rtt": 2689.321,
            "ittl": 0,
            "edst": "193.0.0.164"
          },
          {
            "from": "117.247.236.129",
            "ttl": 254,
            "size": 52,
            "rtt": 1.217,
            "ittl": 0,
            "edst": "193.0.0.164"
          }
        ]
      },
      {
        "hop": 7,
        "result": [
          {
            "from": "117.247.236.129",
            "ttl": 254,
            "size": 52,
            "rtt": 2.315,
            "ittl": 0,
            "edst": "193.0.0.164"
          },
          {
            "from": "218.248.173.65",
            "ttl": 253,
            "size": 52,
            "rtt": 1.324,
            "ittl": 0,
            "edst": "193.0.0.164"
          },
          {
            "from": "218.248.173.65",
            "ttl": 253,
            "size": 52,
            "rtt": 1.945,
            "ittl": 0,
            "edst": "193.0.0.164"
          }
        ]
      },
      {
        "hop": 8,
        "result": [
          {
            "from": "218.248.173.65",
            "ttl": 253,
            "size": 52,
            "rtt": 2.099,
            "ittl": 0,
            "edst": "193.0.0.164"
          },
          {
            "x": "*"
          },
          {
            "x": "*"
          }
        ]
      },
      {
        "hop": 9,
        "result": [
          {
            "x": "*"
          },
          {
            "x": "*"
          },
          {
            "x": "*"
          }
        ]
      },
      {
        "hop": 10,
        "result": [
          {
            "x": "*"
          },
          {
            "x": "*"
          },
          {
            "x": "*"
          }
        ]
      },
      {
        "hop": 11,
        "result": [
          {
            "x": "*"
          },
          {
            "x": "*"
          },
          {
            "x": "*"
          }
        ]
      },
      {
        "hop": 12,
        "result": [
          {
            "late": 34,
            "from": "68.183.247.163",
            "ttl": 53,
            "size": 0,
            "flags": "R"
          },
          {
            "x": "*"
          },
          {
            "from": "68.183.247.163",
            "ttl": 53,
            "size": 4,
            "flags": "SA",
            "hdropts": [
              {
                "mss": 1420
              }
            ],
            "rtt": 60.118
          },
          {
            "from": "68.183.247.163",
            "ttl": 53,
            "size": 4,
            "flags": "SA",
            "hdropts": [
              {
                "mss": 1420
              }
            ],
            "rtt": 55.76
          }
        ]
      }
    ],
    "msm_id": 40383701,
    "prb_id": 55694,
    "timestamp": 1650702061,
    "msm_name": "Traceroute",
    "from": "117.247.236.144",
    "type": "traceroute",
    "group_id": 40383701,
    "stored_timestamp": 1650702156,
    "probe_data": {
      "address_v4": "117.247.236.144",
      "address_v6": null,
      "asn_v4": 9829,
      "asn_v6": null,
      "country_code": "IN",
      "description": "AS55836 Shimla H.P",
      "first_connected": 1597908008,
      "geometry": {
        "type": "Point",
        "coordinates": [
          77.1815,
          31.0895
        ]
      },
      "id": 55694,
      "is_anchor": false,
      "is_public": true,
      "last_connected": 1650721145,
      "prefix_v4": "117.247.236.0/22",
      "prefix_v6": null,
      "status": {
        "id": 1,
        "name": "Connected",
        "since": "2022-04-23T07:50:18Z"
      },
      "status_since": 1650700218,
      "tags": [
        {
          "name": "Fibre",
          "slug": "fibre"
        },
        {
          "name": "Home",
          "slug": "home"
        },
        {
          "name": "NAT",
          "slug": "nat"
        },
        {
          "name": "Native IPv6",
          "slug": "native-ipv6"
        },
        {
          "name": "dual-stack",
          "slug": "dual-stack"
        },
        {
          "name": "IPv4",
          "slug": "ipv4"
        },
        {
          "name": "IPv6",
          "slug": "ipv6"
        },
        {
          "name": "FTTH",
          "slug": "ftth"
        },
        {
          "name": "Double-NAT",
          "slug": "double-nat"
        },
        {
          "name": "CGN",
          "slug": "cgn"
        },
        {
          "name": "system: Resolves A Correctly",
          "slug": "system-resolves-a-correctly"
        },
        {
          "name": "system: Resolves AAAA Incorrectly",
          "slug": "system-resolves-aaaa-incorrectly"
        },
        {
          "name": "system: IPv4 Capable",
          "slug": "system-ipv4-capable"
        },
        {
          "name": "system: IPv4 RFC1918",
          "slug": "system-ipv4-rfc1918"
        },
        {
          "name": "system: V4",
          "slug": "system-v4"
        },
        {
          "name": "system: IPv4 Works",
          "slug": "system-ipv4-works"
        },
        {
          "name": "system: IPv4 Stable 1d",
          "slug": "system-ipv4-stable-1d"
        }
      ],
      "total_uptime": 14045682,
      "type": "Probe"
    }
  }
]