[
  {
    "fw": 5060,
    "mver": "2.5.1",
    "lts": 61,
    "endtime": 1653124897,
    "dst_name": "ra20.tax23.ru",
    "ttr": 487.451957,
    "proto": "TCP",
    "af": 4,
    "size": 0,
    "paris_id": 0,
    "result": [
      {
        "error": "name resolution failed: nodename nor servname provided, or not known"
      }
    ],
    "msm_id": 41311962,
    "prb_id": 1000050,
    "timestamp": 1653124897,
    "msm_name": "Traceroute",
    "from": "124.71.18.26",
    "type": "traceroute",
    "group_id": 41311962,
    "stored_timestamp": 1653125015,
    "probe_data": {
      "address_v4": "124.71.18.26",
      "address_v6": null,
      "asn_v4": 55990,
      "asn_v6": null,
      "country_code": "CN",
      "description": "Huawei - Guangzhou",
      "first_connected": 1574943055,
      "geometry": {
        "type": "Point",
        "coordinates": [
          113.2595,
          23.1275
        ]
      },
      "id": 1000050,
      "is_anchor": false,
      "is_public": true,
      "last_connected": 1653140371,
      "prefix_v4": "124.71.0.0/18",
      "prefix_v6": null,
      "status": {
        "id": 1,
        "name": "Connected",
        "since": "2022-05-18T04:07:45Z"
      },
      "status_since": 1652846865,
      "tags": [
        {
          "name": "system: Resolves A Correctly",
          "slug": "system-resolves-a-correctly"
        },
        {
          "name": "system: IPv4 RFC1918",
          "slug": "system-ipv4-rfc1918"
        },
        {
          "name": "system: Software",
          "slug": "system-software"
        },
        {
          "name": "system: Resolves AAAA Correctly",
          "slug": "system-resolves-aaaa-correctly"
        },
        {
          "name": "system: IPv4 Capable",
          "slug": "system-ipv4-capable"
        },
        {
          "name": "system: IPv4 Works",
          "slug": "system-ipv4-works"
        }
      ],
      "total_uptime": 74056226,
      "type": "Probe"
    }
  },
  {
    "fw": 5060,
    "mver": "2.5.1",
    "lts": 25,
    "endtime": 1653124893,
    "dst_name": "ra20.tax23.ru",
    "ttr": 39.817569,
    "proto": "TCP",
    "af": 4,
    "size": 0,
    "paris_id": 0,
    "result": [
      {
        "error": "name resolution failed: nodename nor servname provided, or not known"
      }
    ],
    "msm_id": 41311962,
    "prb_id": 1000446,
    "timestamp": 1653124893,
    "msm_name": "Traceroute",
    "from": "178.159.242.69",
    "type": "traceroute",
    "group_id": 41311962,
    "stored_timestamp": 1653125057,
    "probe_data": {
      "address_v4": "178.159.242.69",
      "address_v6": null,
      "asn_v4": 6697,
      "asn_v6": null,
      "country_code": "BY",
      "description": "by-ripe-01",
      "first_connected": 1587249623,
      "geometry": {
        "type": "Point",
        "coordinates": [
          27.6395,
          53.8505
        ]
      },
      "id": 1000446,
      "is_anchor": false,
      "is_public": true,
      "last_connected": 1653140054,
      "prefix_v4": "178.159.240.0/21",
      "prefix_v6": null,
      "status": {
        "id": 1,
        "name": "Connected",
        "since": "2022-04-17T03:13:17Z"
      },
      "status_since": 1650165197,
      "tags": [
        {
          "name": "Datacentre",
          "slug": "datacentre"
        },
        {
          "name": "No NAT",
          "slug": "no-nat"
        },
        {
          "name": "IPv4",
          "slug": "ipv4"
        },
        {
          "name": "ActiveCloud",
          "slug": "activecloud"
        },
        {
          "name": "Beltelecom",
          "slug": "beltelecom"
        },
        {
          "name": "system: Resolves A Correctly",
          "slug": "system-resolves-a-correctly"
        },
        {
          "name": "system: Software",
          "slug": "system-software"
        },
        {
          "name": "system: Resolves AAAA Correctly",
          "slug": "system-resolves-aaaa-correctly"
        },
        {
          "name": "system: IPv4 Capable",
          "slug": "system-ipv4-capable"
        },
        {
          "name": "system: IPv4 Works",
          "slug": "system-ipv4-works"
        },
        {
          "name": "system: IPv4 Stable 1d",
          "slug": "system-ipv4-stable-1d"
        },
        {
          "name": "system: IPv4 Stable 30d",
          "slug": "system-ipv4-stable-30d"
        }
      ],
      "total_uptime": 65868648,
      "type": "Probe"
    }
  },
  {
    "fw": 5020,
    "mver": "2.2.1",
    "lts": 16,
    "endtime": 1653124895,
    "dst_name": "ra20.tax23.ru",
    "ttr": 28.259481,
    "proto": "TCP",
    "af": 4,
    "size": 0,
    "paris_id": 0,
    "result": [
      {
        "error": "name resolution failed: nodename nor servname provided, or not known"
      }
    ],
    "msm_id": 41311962,
    "prb_id": 1000871,
    "timestamp": 1653124895,
    "msm_name": "Traceroute",
    "from": "188.243.246.159",
    "type": "traceroute",
    "group_id": 41311962,
    "stored_timestamp": 1653125014,
    "probe_data": {
      "address_v4": "188.243.246.159",
      "address_v6": null,
      "asn_v4": 35807,
      "asn_v6": null,
      "country_code": "RU",
      "description": null,
      "first_connected": 1597411519,
      "geometry": {
        "type": "Point",
        "coordinates": [
          30.2205,
          59.9475
        ]
      },
      "id": 1000871,
      "is_anchor": false,
      "is_public": true,
      "last_connected": 1653140238,
      "prefix_v4": "188.243.246.0/24",
      "prefix_v6": null,
      "status": {
        "id": 1,
        "name": "Connected",
        "since": "2022-04-26T01:25:48Z"
      },
      "status_since": 1650936348,
      "tags": [
        {
          "name": "system: IPv4 Stable 90d",
          "slug": "system-ipv4-stable-90d"
        },
        {
          "name": "system: Resolver Mangles Case",
          "slug": "system-resolver-mangles-case"
        },
        {
          "name": "system: IPv4 RFC1918",
          "slug": "system-ipv4-rfc1918"
        },
        {
          "name": "system: Software",
          "slug": "system-software"
        },
        {
          "name": "system: IPv4 Capable",
          "slug": "system-ipv4-capable"
        },
        {
          "name": "system: IPv4 Works",
          "slug": "system-ipv4-works"
        },
        {
          "name": "system: IPv4 Stable 1d",
          "slug": "system-ipv4-stable-1d"
        },
        {
          "name": "system: IPv4 Stable 30d",
          "slug": "system-ipv4-stable-30d"
        }
      ],
      "total_uptime": 52728815,
      "type": "Probe"
    }
  },
  {
    "fw": 5060,
    "mver": "2.5.1",
    "lts": 15,
    "endtime": 1653124896,
    "dst_name": "ra20.tax23.ru",
    "ttr": 91.483146,
    "proto": "TCP",
    "af": 4,
    "size": 0,
    "paris_id": 0,
    "result": [
      {
        "error": "name resolution failed: nodename nor servname provided, or not known"
      }
    ],
    "msm_id": 41311962,
    "prb_id": 12654,
    "timestamp": 1653124896,
    "msm_name": "Traceroute",
    "from": "193.109.160.170",
    "type": "traceroute",
    "group_id": 41311962,
    "stored_timestamp": 1653124966,
    "probe_data": {
      "address_v4": null,
      "address_v6": null,
      "asn_v4": 45025,
      "asn_v6": null,
      "country_code": "UA",
      "description": null,
      "first_connected": 1380886958,
      "geometry": {
        "type": "Point",
        "coordinates": [
          37.9295,
          48.0495
        ]
      },
      "id": 12654,
      "is_anchor": false,
      "is_public": false,
      "last_connected": 1653140041,
      "prefix_v4": "193.109.160.0/24",
      "prefix_v6": null,
      "status": {
        "id": 1,
        "name": "Connected",
        "since": "2022-05-18T17:44:43Z"
      },
      "status_since": 1652895883,
      "tags": [
        {
          "name": "NAT",
          "slug": "nat"
        },
        {
          "name": "system: Auto GEOIP city",
          "slug": "system-auto-geoip-city"
        },
        {
          "name": "system: Resolves A Correctly",
          "slug": "system-resolves-a-correctly"
        },
        {
          "name": "system: IPv4 RFC1918",
          "slug": "system-ipv4-rfc1918"
        },
        {
          "name": "system: V3",
          "slug": "system-v3"
        },
        {
          "name": "system: Resolves AAAA Correctly",
          "slug": "system-resolves-aaaa-correctly"
        },
        {
          "name": "system: IPv4 Capable",
          "slug": "system-ipv4-capable"
        },
        {
          "name": "system: IPv4 Works",
          "slug": "system-ipv4-works"
        }
      ],
      "total_uptime": 218366592,
      "type": "Probe"
    }
  },
  {
    "fw": 5060,
    "mver": "2.5.1",
    "lts": 18,
    "endtime": 1653124896,
    "dst_name": "ra20.tax23.ru",
    "ttr": 44.243431,
    "proto": "TCP",
    "af": 4,
    "size": 0,
    "paris_id": 0,
    "result": [
      {
        "error": "name resolution failed: nodename nor servname provided, or not known"
      }
    ],
    "msm_id": 41311962,
    "prb_id": 13452,
    "timestamp": 1653124896,
    "msm_name": "Traceroute",
    "from": "185.146.212.89",
    "type": "traceroute",
    "group_id": 41311962,
    "stored_timestamp": 1653125018,
    "probe_data": {
      "address_v4": "185.146.212.89",
      "address_v6": null,
      "asn_v4": 197159,
      "asn_v6": null,
      "country_code": "UA",
      "description": null,
      "first_connected": 1383052152,
      "geometry": {
        "type": "Point",
        "coordinates": [
          34.0895,
          44.9885
        ]
      },
      "id": 13452,
      "is_anchor": false,
      "is_public": true,
      "last_connected": 1653140042,
      "prefix_v4": "185.146.212.0/24",
      "prefix_v6": null,
      "status": {
        "id": 1,
        "name": "Connected",
        "since": "2022-05-09T05:22:10Z"
      },
      "status_since": 1652073730,
      "tags": [
        {
          "name": "NAT",
          "slug": "nat"
        },
        {
          "name": "system: Resolves A Correctly",
          "slug": "system-resolves-a-correctly"
        },
        {
          "name": "system: IPv4 RFC1918",
          "slug": "system-ipv4-rfc1918"
        },
        {
          "name": "system: V3",
          "slug": "system-v3"
        },
        {
          "name": "system: Resolves AAAA Correctly",
          "slug": "system-resolves-aaaa-correctly"
        },
        {
          "name": "system: IPv4 Capable",
          "slug": "system-ipv4-capable"
        },
        {
          "name": "system: IPv4 Works",
          "slug": "system-ipv4-works"
        },
        {
          "name": "system: IPv4 Stable 1d",
          "slug": "system-ipv4-stable-1d"
        }
      ],
      "total_uptime": 170814458,
      "type": "Probe"
    }
  },
  {
    "fw": 5060,
    "mver": "2.5.1",
    "lts": 109,
    "endtime": 1653124897,
    "dst_name": "ra20.tax23.ru",
    "ttr": 515.761009,
    "proto": "TCP",
    "af": 4,
    "size": 0,
    "paris_id": 0,
    "result": [
      {
        "error": "name resolution failed: nodename nor servname provided, or not known"
      }
    ],
    "msm_id": 41311962,
    "prb_id": 14778,
    "timestamp": 1653124897,
    "msm_name": "Traceroute",
    "from": "180.150.57.72",
    "type": "traceroute",
    "group_id": 41311962,
    "stored_timestamp": 1653125002,
    "probe_data": {
      "address_v4": "180.150.57.72",
      "address_v6": "fd41:de2:37c:0:6666:b3ff:feb0:edde",
      "asn_v4": 4764,
      "asn_v6": null,
      "country_code": "AU",
      "description": null,
      "first_connected": 1392865281,
      "geometry": {
        "type": "Point",
        "coordinates": [
          144.4505,
          -37.2285
        ]
      },
      "id": 14778,
      "is_anchor": false,
      "is_public": true,
      "last_connected": 1653140475,
      "prefix_v4": "180.150.56.0/23",
      "prefix_v6": null,
      "status": {
        "id": 1,
        "name": "Connected",
        "since": "2022-05-11T08:31:03Z"
      },
      "status_since": 1652257863,
      "tags": [
        {
          "name": "NAT",
          "slug": "nat"
        },
        {
          "name": "system: IPv4 Stable 90d",
          "slug": "system-ipv4-stable-90d"
        },
        {
          "name": "system: Resolves A Correctly",
          "slug": "system-resolves-a-correctly"
        },
        {
          "name": "system: IPv4 RFC1918",
          "slug": "system-ipv4-rfc1918"
        },
        {
          "name": "system: V3",
          "slug": "system-v3"
        },
        {
          "name": "system: Resolves AAAA Correctly",
          "slug": "system-resolves-aaaa-correctly"
        },
        {
          "name": "system: IPv4 Capable",
          "slug": "system-ipv4-capable"
        },
        {
          "name": "system: IPv6 Capable",
          "slug": "system-ipv6-capable"
        },
        {
          "name": "system: IPv6 ULA",
          "slug": "system-ipv6-ula"
        },
        {
          "name": "system: IPv4 Works",
          "slug": "system-ipv4-works"
        },
        {
          "name": "system: IPv4 Stable 1d",
          "slug": "system-ipv4-stable-1d"
        },
        {
          "name": "system: IPv4 Stable 30d",
          "slug": "system-ipv4-stable-30d"
        }
      ],
      "total_uptime": 217217042,
      "type": "Probe"
    }
  },
  {
    "fw": 5060,
    "mver": "2.5.1",
    "lts": 3,
    "endtime": 1653124896,
    "dst_name": "ra20.tax23.ru",
    "ttr": 674.055562,
    "proto": "TCP",
    "af": 4,
    "size": 0,
    "paris_id": 0,
    "result": [
      {
        "error": "name resolution failed: nodename nor servname provided, or not known"
      }
    ],
    "msm_id": 41311962,
    "prb_id": 17946,
    "timestamp": 1653124896,
    "msm_name": "Traceroute",
    "from": "73.52.80.84",
    "type": "traceroute",
    "group_id": 41311962,
    "stored_timestamp": 1653125018,
    "probe_data": {
      "address_v4": "73.52.80.84",
      "address_v6": null,
      "asn_v4": 7922,
      "asn_v6": null,
      "country_code": "US",
      "description": "Mount Union, PA - Comcast - rural cable ISP service",
      "first_connected": 1403138911,
      "geometry": {
        "type": "Point",
        "coordinates": [
          -77.8805,
          40.3805
        ]
      },
      "id": 17946,
      "is_anchor": false,
      "is_public": true,
      "last_connected": 1653140182,
      "prefix_v4": "73.0.0.0/8",
      "prefix_v6": null,
      "status": {
        "id": 1,
        "name": "Connected",
        "since": "2022-04-29T08:28:57Z"
      },
      "status_since": 1651220937,
      "tags": [
        {
          "name": "system: IPv4 Stable 90d",
          "slug": "system-ipv4-stable-90d"
        },
        {
          "name": "system: Resolves A Correctly",
          "slug": "system-resolves-a-correctly"
        },
        {
          "name": "system: IPv4 RFC1918",
          "slug": "system-ipv4-rfc1918"
        },
        {
          "name": "system: V3",
          "slug": "system-v3"
        },
        {
          "name": "system: Resolves AAAA Correctly",
          "slug": "system-resolves-aaaa-correctly"
        },
        {
          "name": "system: IPv4 Capable",
          "slug": "system-ipv4-capable"
        },
        {
          "name": "system: IPv4 Works",
          "slug": "system-ipv4-works"
        },
        {
          "name": "system: IPv4 Stable 1d",
          "slug": "system-ipv4-stable-1d"
        },
        {
          "name": "system: IPv4 Stable 30d",
          "slug": "system-ipv4-stable-30d"
        }
      ],
      "total_uptime": 219566000,
      "type": "Probe"
    }
  },
  {
    "fw": 5060,
    "mver": "2.5.1",
    "lts": 15,
    "endtime": 1653124895,
    "dst_name": "ra20.tax23.ru",
    "ttr": 29.387109,
    "proto": "TCP",
    "af": 4,
    "size": 0,
    "paris_id": 0,
    "result": [
      {
        "error": "name resolution failed: nodename nor servname provided, or not known"
      }
    ],
    "msm_id": 41311962,
    "prb_id": 19977,
    "timestamp": 1653124895,
    "msm_name": "Traceroute",
    "from": "178.127.169.203",
    "type": "traceroute",
    "group_id": 41311962,
    "stored_timestamp": 1653125009,
    "probe_data": {
      "address_v4": "178.127.169.203",
      "address_v6": null,
      "asn_v4": 6697,
      "asn_v6": null,
      "country_code": "BY",
      "description": "Chupaka's Probe",
      "first_connected": 1417180314,
      "geometry": {
        "type": "Point",
        "coordinates": [
          27.6605,
          53.8705
        ]
      },
      "id": 19977,
      "is_anchor": false,
      "is_public": true,
      "last_connected": 1653140085,
      "prefix_v4": "178.127.128.0/17",
      "prefix_v6": null,
      "status": {
        "id": 1,
        "name": "Connected",
        "since": "2022-05-19T11:48:41Z"
      },
      "status_since": 1652960921,
      "tags": [
        {
          "name": "Fibre",
          "slug": "fibre"
        },
        {
          "name": "Home",
          "slug": "home"
        },
        {
          "name": "No NAT",
          "slug": "no-nat"
        },
        {
          "name": "IPv6 Tunnel",
          "slug": "ipv6-tunnel"
        },
        {
          "name": "IPv4",
          "slug": "ipv4"
        },
        {
          "name": "6to4",
          "slug": "6to4"
        },
        {
          "name": "Native IPv4",
          "slug": "native-ipv4"
        },
        {
          "name": "iwantbcp38compliancetesting",
          "slug": "iwantbcp38compliancetesting"
        },
        {
          "name": "system: Resolves A Correctly",
          "slug": "system-resolves-a-correctly"
        },
        {
          "name": "system: V3",
          "slug": "system-v3"
        },
        {
          "name": "system: Resolves AAAA Correctly",
          "slug": "system-resolves-aaaa-correctly"
        },
        {
          "name": "system: IPv4 Capable",
          "slug": "system-ipv4-capable"
        },
        {
          "name": "system: IPv4 Works",
          "slug": "system-ipv4-works"
        },
        {
          "name": "system: IPv4 Stable 1d",
          "slug": "system-ipv4-stable-1d"
        },
        {
          "name": "system: IPv4 Stable 30d",
          "slug": "system-ipv4-stable-30d"
        }
      ],
      "total_uptime": 206312312,
      "type": "Probe"
    }
  },
  {
    "fw": 5040,
    "mver": "2.4.1",
    "lts": 2,
    "endtime": 1653124894,
    "dst_name": "ra20.tax23.ru",
    "ttr": 176.921231,
    "proto": "TCP",
    "af": 4,
    "size": 0,
    "paris_id": 0,
    "result": [
      {
        "error": "name resolution failed: nodename nor servname provided, or not known"
      }
    ],
    "msm_id": 41311962,
    "prb_id": 22635,
    "timestamp": 1653124894,
    "msm_name": "Traceroute",
    "from": "91.122.31.155",
    "type": "traceroute",
    "group_id": 41311962,
    "stored_timestamp": 1653124961,
    "probe_data": {
      "address_v4": "91.122.31.155",
      "address_v6": null,
      "asn_v4": 12389,
      "asn_v6": null,
      "country_code": "RU",
      "description": "",
      "first_connected": 1433882522,
      "geometry": {
        "type": "Point",
        "coordinates": [
          30.2085,
          59.9995
        ]
      },
      "id": 22635,
      "is_anchor": false,
      "is_public": true,
      "last_connected": 1653140045,
      "prefix_v4": "91.122.0.0/17",
      "prefix_v6": null,
      "status": {
        "id": 1,
        "name": "Connected",
        "since": "2021-12-15T14:10:21Z"
      },
      "status_since": 1639577421,
      "tags": [
        {
          "name": "system: IPv4 Stable 90d",
          "slug": "system-ipv4-stable-90d"
        },
        {
          "name": "system: Resolves A Correctly",
          "slug": "system-resolves-a-correctly"
        },
        {
          "name": "system: V3",
          "slug": "system-v3"
        },
        {
          "name": "system: Resolves AAAA Correctly",
          "slug": "system-resolves-aaaa-correctly"
        },
        {
          "name": "system: IPv4 Capable",
          "slug": "system-ipv4-capable"
        },
        {
          "name": "system: IPv4 Works",
          "slug": "system-ipv4-works"
        },
        {
          "name": "system: IPv4 Stable 1d",
          "slug": "system-ipv4-stable-1d"
        },
        {
          "name": "system: IPv4 Stable 30d",
          "slug": "system-ipv4-stable-30d"
        }
      ],
      "total_uptime": 213557050,
      "type": "Probe"
    }
  },
  {
    "fw": 5060,
    "mver": "2.5.1",
    "lts": 21,
    "endtime": 1653124895,
    "dst_name": "ra20.tax23.ru",
    "ttr": 66.12168,
    "proto": "TCP",
    "af": 4,
    "size": 0,
    "paris_id": 0,
    "result": [
      {
        "error": "name resolution failed: nodename nor servname provided, or not known"
      }
    ],
    "msm_id": 41311962,
    "prb_id": 23719,
    "timestamp": 1653124895,
    "msm_name": "Traceroute",
    "from": "91.192.128.242",
    "type": "traceroute",
    "group_id": 41311962,
    "stored_timestamp": 1653125018,
    "probe_data": {
      "address_v4": null,
      "address_v6": null,
      "asn_v4": 31633,
      "asn_v6": null,
      "country_code": "UA",
      "description": "Lan-Telecom",
      "first_connected": 1436607069,
      "geometry": {
        "type": "Point",
        "coordinates": [
          31.0975,
          46.6215
        ]
      },
      "id": 23719,
      "is_anchor": false,
      "is_public": false,
      "last_connected": 1653140107,
      "prefix_v4": "91.192.128.0/24",
      "prefix_v6": null,
      "status": {
        "id": 1,
        "name": "Connected",
        "since": "2022-05-10T00:29:54Z"
      },
      "status_since": 1652142594,
      "tags": [
        {
          "name": "Cable",
          "slug": "cable"
        },
        {
          "name": "No NAT",
          "slug": "no-nat"
        },
        {
          "name": "IPv4",
          "slug": "ipv4"
        },
        {
          "name": "ISP",
          "slug": "isp"
        },
        {
          "name": "system: IPv4 Stable 90d",
          "slug": "system-ipv4-stable-90d"
        },
        {
          "name": "system: Resolves A Correctly",
          "slug": "system-resolves-a-correctly"
        },
        {
          "name": "system: V3",
          "slug": "system-v3"
        },
        {
          "name": "system: Resolves AAAA Correctly",
          "slug": "system-resolves-aaaa-correctly"
        },
        {
          "name": "system: IPv4 Capable",
          "slug": "system-ipv4-capable"
        },
        {
          "name": "system: IPv4 Works",
          "slug": "system-ipv4-works"
        },
        {
          "name": "system: IPv4 Stable 1d",
          "slug": "system-ipv4-stable-1d"
        },
        {
          "name": "system: IPv4 Stable 30d",
          "slug": "system-ipv4-stable-30d"
        }
      ],
      "total_uptime": 167326057,
      "type": "Probe"
    }
  },
  {
    "fw": 5060,
    "mver": "2.5.1",
    "lts": 102,
    "endtime": 1653124897,
    "dst_name": "ra20.tax23.ru",
    "ttr": 426.552657,
    "proto": "TCP",
    "af": 4,
    "size": 0,
    "paris_id": 0,
    "result": [
      {
        "error": "name resolution failed: nodename nor servname provided, or not known"
      }
    ],
    "msm_id": 41311962,
    "prb_id": 31881,
    "timestamp": 1653124897,
    "msm_name": "Traceroute",
    "from": "217.95.138.213",
    "type": "traceroute",
    "group_id": 41311962,
    "stored_timestamp": 1653125018,
    "probe_data": {
      "address_v4": null,
      "address_v6": null,
      "asn_v4": 3320,
      "asn_v6": 3320,
      "country_code": "DE",
      "description": "",
      "first_connected": 1482091177,
      "geometry": {
        "type": "Point",
        "coordinates": [
          9.1315,
          51.1175
        ]
      },
      "id": 31881,
      "is_anchor": false,
      "is_public": false,
      "last_connected": 1653140060,
      "prefix_v4": "217.80.0.0/12",
      "prefix_v6": "2003::/19",
      "status": {
        "id": 1,
        "name": "Connected",
        "since": "2022-05-21T02:16:05Z"
      },
      "status_since": 1653099365,
      "tags": [
        {
          "name": "Home",
          "slug": "home"
        },
        {
          "name": "Native IPv6",
          "slug": "native-ipv6"
        },
        {
          "name": "dual-stack",
          "slug": "dual-stack"
        },
        {
          "name": "IPv4",
          "slug": "ipv4"
        },
        {
          "name": "IPv6",
          "slug": "ipv6"
        },
        {
          "name": "VDSL2",
          "slug": "vdsl2"
        },
        {
          "name": "DTAG",
          "slug": "dtag"
        },
        {
          "name": "Native IPv4",
          "slug": "native-ipv4"
        },
        {
          "name": "system: IPv4 Stable 90d",
          "slug": "system-ipv4-stable-90d"
        },
        {
          "name": "system: IPv6 Stable 1d",
          "slug": "system-ipv6-stable-1d"
        },
        {
          "name": "system: Resolves A Correctly",
          "slug": "system-resolves-a-correctly"
        },
        {
          "name": "system: IPv6 Stable 30d",
          "slug": "system-ipv6-stable-30d"
        },
        {
          "name": "system: IPv4 RFC1918",
          "slug": "system-ipv4-rfc1918"
        },
        {
          "name": "system: V3",
          "slug": "system-v3"
        },
        {
          "name": "system: Resolves AAAA Correctly",
          "slug": "system-resolves-aaaa-correctly"
        },
        {
          "name": "system: IPv4 Capable",
          "slug": "system-ipv4-capable"
        },
        {
          "name": "system: IPv6 Capable",
          "slug": "system-ipv6-capable"
        },
        {
          "name": "system: IPv6 Works",
          "slug": "system-ipv6-works"
        },
        {
          "name": "system: IPv6 Stable 90d",
          "slug": "system-ipv6-stable-90d"
        },
        {
          "name": "system: IPv4 Works",
          "slug": "system-ipv4-works"
        },
        {
          "name": "system: IPv4 Stable 1d",
          "slug": "system-ipv4-stable-1d"
        },
        {
          "name": "system: IPv4 Stable 30d",
          "slug": "system-ipv4-stable-30d"
        }
      ],
      "total_uptime": 168771087,
      "type": "Probe"
    }
  },
  {
    "fw": 5060,
    "mver": "2.5.1",
    "lts": 18,
    "endtime": 1653124895,
    "dst_name": "ra20.tax23.ru",
    "ttr": 71.412334,
    "proto": "TCP",
    "af": 4,
    "size": 0,
    "paris_id": 0,
    "result": [
      {
        "error": "name resolution failed: nodename nor servname provided, or not known"
      }
    ],
    "msm_id": 41311962,
    "prb_id": 52016,
    "timestamp": 1653124895,
    "msm_name": "Traceroute",
    "from": "91.234.167.10",
    "type": "traceroute",
    "group_id": 41311962,
    "stored_timestamp": 1653125037,
    "probe_data": {
      "address_v4": "91.234.167.10",
      "address_v6": null,
      "asn_v4": 49478,
      "asn_v6": null,
      "country_code": "RU",
      "description": "prober-adg",
      "first_connected": 1556441712,
      "geometry": {
        "type": "Point",
        "coordinates": [
          38.9375,
          44.9805
        ]
      },
      "id": 52016,
      "is_anchor": false,
      "is_public": true,
      "last_connected": 1653140466,
      "prefix_v4": "91.234.164.0/22",
      "prefix_v6": null,
      "status": {
        "id": 1,
        "name": "Connected",
        "since": "2022-05-20T12:11:57Z"
      },
      "status_since": 1653048717,
      "tags": [
        {
          "name": "system: IPv4 Stable 90d",
          "slug": "system-ipv4-stable-90d"
        },
        {
          "name": "system: Resolves A Correctly",
          "slug": "system-resolves-a-correctly"
        },
        {
          "name": "system: IPv4 RFC1918",
          "slug": "system-ipv4-rfc1918"
        },
        {
          "name": "system: V4",
          "slug": "system-v4"
        },
        {
          "name": "system: Resolves AAAA Correctly",
          "slug": "system-resolves-aaaa-correctly"
        },
        {
          "name": "system: IPv4 Capable",
          "slug": "system-ipv4-capable"
        },
        {
          "name": "system: IPv4 Works",
          "slug": "system-ipv4-works"
        },
        {
          "name": "system: IPv4 Stable 1d",
          "slug": "system-ipv4-stable-1d"
        },
        {
          "name": "system: IPv4 Stable 30d",
          "slug": "system-ipv4-stable-30d"
        }
      ],
      "total_uptime": 89027807,
      "type": "Probe"
    }
  },
  {
    "fw": 5060,
    "mver": "2.5.1",
    "lts": 19,
    "endtime": 1653124897,
    "dst_name": "ra20.tax23.ru",
    "ttr": 409.966042,
    "proto": "TCP",
    "af": 4,
    "size": 0,
    "paris_id": 0,
    "result": [
      {
        "error": "name resolution failed: nodename nor servname provided, or not known"
      }
    ],
    "msm_id": 41311962,
    "prb_id": 52835,
    "timestamp": 1653124897,
    "msm_name": "Traceroute",
    "from": "111.119.193.108",
    "type": "traceroute",
    "group_id": 41311962,
    "stored_timestamp": 1653125001,
    "probe_data": {
      "address_v4": "111.119.193.108",
      "address_v6": "fd01::1:d1ff:feab:123f",
      "asn_v4": 45194,
      "asn_v6": null,
      "country_code": "IN",
      "description": "ftver_ripe_probe_1",
      "first_connected": 1602230262,
      "geometry": {
        "type": "Point",
        "coordinates": [
          73.9185,
          15.2995
        ]
      },
      "id": 52835,
      "is_anchor": false,
      "is_public": true,
      "last_connected": 1653140432,
      "prefix_v4": "111.119.193.0/24",
      "prefix_v6": null,
      "status": {
        "id": 1,
        "name": "Connected",
        "since": "2022-05-21T12:33:02Z"
      },
      "status_since": 1653136382,
      "tags": [
        {
          "name": "system: Resolves A Correctly",
          "slug": "system-resolves-a-correctly"
        },
        {
          "name": "system: IPv4 RFC1918",
          "slug": "system-ipv4-rfc1918"
        },
        {
          "name": "system: V4",
          "slug": "system-v4"
        },
        {
          "name": "system: Resolves AAAA Correctly",
          "slug": "system-resolves-aaaa-correctly"
        },
        {
          "name": "system: IPv4 Capable",
          "slug": "system-ipv4-capable"
        },
        {
          "name": "system: IPv6 Capable",
          "slug": "system-ipv6-capable"
        },
        {
          "name": "system: IPv6 ULA",
          "slug": "system-ipv6-ula"
        },
        {
          "name": "system: IPv4 Works",
          "slug": "system-ipv4-works"
        }
      ],
      "total_uptime": 45919004,
      "type": "Probe"
    }
  },
  {
    "fw": 5060,
    "mver": "2.5.1",
    "lts": 4,
    "endtime": 1653124896,
    "dst_name": "ra20.tax23.ru",
    "ttr": 42.365416,
    "proto": "TCP",
    "af": 4,
    "size": 0,
    "paris_id": 0,
    "result": [
      {
        "error": "name resolution failed: nodename nor servname provided, or not known"
      }
    ],
    "msm_id": 41311962,
    "prb_id": 53076,
    "timestamp": 1653124896,
    "msm_name": "Traceroute",
    "from": "178.124.162.164",
    "type": "traceroute",
    "group_id": 41311962,
    "stored_timestamp": 1653124968,
    "probe_data": {
      "address_v4": "178.124.162.164",
      "address_v6": "2a02:220f:2000:bb00:1:aff:fe1d:c832",
      "asn_v4": 6697,
      "asn_v6": 6697,
      "country_code": "BY",
      "description": "via Beltelecom internet provider",
      "first_connected": 1624275764,
      "geometry": {
        "type": "Point",
        "coordinates": [
          27.5605,
          53.9005
        ]
      },
      "id": 53076,
      "is_anchor": false,
      "is_public": true,
      "last_connected": 1653140064,
      "prefix_v4": "178.124.162.0/24",
      "prefix_v6": "2a02:2208::/29",
      "status": {
        "id": 1,
        "name": "Connected",
        "since": "2022-05-11T08:52:05Z"
      },
      "status_since": 1652259125,
      "tags": [
        {
          "name": "system: IPv6 Stable 1d",
          "slug": "system-ipv6-stable-1d"
        },
        {
          "name": "system: Resolves A Correctly",
          "slug": "system-resolves-a-correctly"
        },
        {
          "name": "system: IPv4 RFC1918",
          "slug": "system-ipv4-rfc1918"
        },
        {
          "name": "system: V4",
          "slug": "system-v4"
        },
        {
          "name": "system: Resolves AAAA Correctly",
          "slug": "system-resolves-aaaa-correctly"
        },
        {
          "name": "system: IPv4 Capable",
          "slug": "system-ipv4-capable"
        },
        {
          "name": "system: IPv6 Capable",
          "slug": "system-ipv6-capable"
        },
        {
          "name": "system: IPv6 Works",
          "slug": "system-ipv6-works"
        },
        {
          "name": "system: IPv4 Works",
          "slug": "system-ipv4-works"
        },
        {
          "name": "system: IPv4 Stable 1d",
          "slug": "system-ipv4-stable-1d"
        }
      ],
      "total_uptime": 27783209,
      "type": "Probe"
    }
  },
  {
    "fw": 5060,
    "mver": "2.5.1",
    "lts": 94,
    "endtime": 1653124897,
    "dst_name": "ra20.tax23.ru",
    "ttr": 41.274292,
    "proto": "TCP",
    "af": 4,
    "size": 0,
    "paris_id": 0,
    "result": [
      {
        "error": "name resolution failed: nodename nor servname provided, or not known"
      }
    ],
    "msm_id": 41311962,
    "prb_id": 55193,
    "timestamp": 1653124897,
    "msm_name": "Traceroute",
    "from": "46.20.76.63",
    "type": "traceroute",
    "group_id": 41311962,
    "stored_timestamp": 1653125012,
    "probe_data": {
      "address_v4": "46.20.76.63",
      "address_v6": null,
      "asn_v4": 51813,
      "asn_v6": null,
      "country_code": "RU",
      "description": "AlterCPA Office, Saransk, Mordovia, Russia",
      "first_connected": 1585325650,
      "geometry": {
        "type": "Point",
        "coordinates": [
          45.2615,
          54.1885
        ]
      },
      "id": 55193,
      "is_anchor": false,
      "is_public": true,
      "last_connected": 1653140050,
      "prefix_v4": "46.20.76.0/22",
      "prefix_v6": null,
      "status": {
        "id": 1,
        "name": "Connected",
        "since": "2022-05-11T08:38:02Z"
      },
      "status_since": 1652258282,
      "tags": [
        {
          "name": "Cable",
          "slug": "cable"
        },
        {
          "name": "Office",
          "slug": "office"
        },
        {
          "name": "NAT",
          "slug": "nat"
        },
        {
          "name": "IPv4",
          "slug": "ipv4"
        },
        {
          "name": "FTTH",
          "slug": "ftth"
        },
        {
          "name": "system: Resolves A Correctly",
          "slug": "system-resolves-a-correctly"
        },
        {
          "name": "system: IPv4 RFC1918",
          "slug": "system-ipv4-rfc1918"
        },
        {
          "name": "system: V4",
          "slug": "system-v4"
        },
        {
          "name": "system: Resolves AAAA Correctly",
          "slug": "system-resolves-aaaa-correctly"
        },
        {
          "name": "system: IPv4 Capable",
          "slug": "system-ipv4-capable"
        },
        {
          "name": "system: IPv4 Works",
          "slug": "system-ipv4-works"
        },
        {
          "name": "system: IPv4 Stable 1d",
          "slug": "system-ipv4-stable-1d"
        },
        {
          "name": "system: IPv4 Stable 30d",
          "slug": "system-ipv4-stable-30d"
        }
      ],
      "total_uptime": 53956815,
      "type": "Probe"
    }
  }
]